Workbook

Sheet HOW TO USE
A3: SHEET | B3: PURPOSE | C3: HOW TO USE
A4: Income Tracker | B4: Record all service revenue with GST & Discounts | C4: Enter each payment with service type
A5: Expense Tracker | B5: Track all business expenses with GST | C5: Log every expense with category
A6: Employee Salaries | B6: Track employee salary payments | C6: Monthly salary - PF/ESI/HRA default 0
A7: Contractor Payments | B7: Track contractor payouts with TDS | C7: Gross amount, TDS deduction, net payable
A8: Stock Purchases | B8: Track inventory purchases | C8: Vendor purchases with GST
A9: Machines & Equipment | B9: Asset register | C9: Add machines with Invoice & GST details
A10: Machine Maintenance | B10: Track repairs/servicing | C10: Log maintenance with status
A11: Chemicals Stock | B11: Chemical inventory | C11: Track opening, added, used, closing stock
A12: Accessories Stock | B12: Consumables inventory | C12: Track stock levels
A13: Stock Transactions | B13: Stock movement log | C13: Record purchases and usage
A14: Income Summary | B14: Revenue reports | C14: Auto-calculated from Income Tracker
... A19: Dashboard | B19: Visual overview | C19: Key metrics and charts

Sheet Income Tracker
A1: Date | B1: Invoice No | C1: Customer Name | D1: Service Type | E1: Project Type | F1: Project Name | G1: Base Amount (₹) | H1: Discount % | I1: Discount Amount (₹) | J1: Amount After Discount (₹) | K1: GST % | L1: GST Amount (₹) | M1: Total Amount (₹) | N1: Payment Mode | O1: Payment Status | P1: Notes
A2: 45665 | B2: INV-2025-1001 | C2: Rajesh Kumar | D2: Pest Control | E2: Commercial | F2: Tech Park | G2: 55884 | H2: 0.1 | I2: =G2*H2 | J2: =G2-I2 | K2: 0.18 | L2: =J2*K2 | M2: =J2+L2 | N2: Card | O2: Received
A3: 45667 | B3: INV-2025-1002 | C3: Priya Sharma | D3: AC Service | E3: Apartment Bulk | F3: Green Valley Apartments | G3: 66717 | H3: 0 | I3: =G3*H3 | J3: =G3-I3 | K3: 0.18 | L3: =J3*K3 | M3: =J3+L3 | N3: Bank Transfer | O3: Pending
A4: 45682 | B4: INV-2025-1003 | C4: Amit Patel | D4: Deep Cleaning | E4: Individual | G4: 9253 | H4: 0 | I4: =G4*H4 | J4: =G4-I4 | K4: 0.18 | L4: =J4*K4 | M4: =J4+L4 | N4: UPI | O4: Pending
A5: 45673 | B5: INV-2025-1004 | C5: Sunita Reddy | D5: Deep Cleaning | E5: Apartment Bulk | F5: Green Valley Apartments | G5: 74496 | H5: 0 | I5: =G5*H5 | J5: =G5-I5 | K5: 0.18 | L5: =J5*K5 | M5: =J5+L5 | N5: Cash | O5: Pending
A6: 45683 | B6: INV-2025-1005 | C6: Vikram Singh | D6: Deep Cleaning | E6: Apartment Bulk | F6: Green Valley Apartments | G6: 164907 | H6: 0.1 | I6: =G6*H6 | J6: =G6-I6 | K6: 0.18 | L6: =J6*K6 | M6: =J6+L6 | N6: UPI | O6: Received
A7: 45667 | B7: INV-2025-1006 | C7: Deepa Nair | D7: Regular Cleaning | E7: Apartment Bulk | F7: Green Valley Apartments | G7: 128923 | H7: 0 | I7: =G7*H7 | J7: =G7-I7 | K7: 0.18 | L7: =J7*K7 | M7: =J7+L7 | N7: Cash | O7: Received
A8: 45661 | B8: INV-2025-1007 | C8: Karthik Iyer | D8: Painting | E8: Individual | G8: 20806 | H8: 0 | I8: =G8*H8 | J8: =G8-I8 | K8: 0.18 | L8: =J8*K8 | M8: =J8+L8 | N8: UPI | O8: Pending
A9: 45681 | B9: INV-2025-1008 | C9: Meena Gupta | D9: Plumbing | E9: Individual | G9: 6516 | H9: 0.05 | I9: =G9*H9 | J9: =G9-I9 | K9: 0.18 | L9: =J9*K9 | M9: =J9+L9 | N9: Card | O9: Received
A10: 45660 | B10: INV-2025-1009 | C10: Rahul Verma | D10: Plumbing | E10: Commercial | F10: Tech Park | G10: 171185 | H10: 0.1 | I10: =G10*H10 | J10: =G10-I10 | K10: 0.18 | L10: =J10*K10 | M10: =J10+L10 | N10: Card | O10: Received
A11: 45679 | B11: INV-2025-1010 | C11: Anjali Menon | D11: AC Service | E11: Apartment Bulk | F11: Green Valley Apartments | G11: 123051 | H11: 0 | I11: =G11*H11 | J11: =G11-I11 | K11: 0.18 | L11: =J11*K11 | M11: =J11+L11 | N11: Card | O11: Received
A12: 45662 | B12: INV-2025-1011 | C12: Suresh Rao | D12: AC Service | E12: Individual | G12: 2878 | H12: 0.1 | I12: =G12*H12 | J12: =G12-I12 | K12: 0.18 | L12: =J12*K12 | M12: =J12+L12 | N12: UPI | O12: Received
A13: 45679 | B13: INV-2025-1012 | C13: Lakshmi Pillai | D13: Painting | E13: Individual | G13: 8288 | H13: 0.05 | I13: =G13*H13 | J13: =G13-I13 | K13: 0.18 | L13: =J13*K13 | M13: =J13+L13 | N13: Card | O13: Pending
A14: 45678 | B14: INV-2025-1013 | C14: Arun Krishnan | D14: Deep Cleaning | E14: Individual | G14: 2403 | H14: 0 | I14: =G14*H14 | J14: =G14-I14 | K14: 0.18 | L14: =J14*K14 | M14: =J14+L14 | N14: Bank Transfer | O14: Pending
A15: 45676 | B15: INV-2025-1014 | C15: Kavitha Srinivasan | D15: Carpentry | E15: Individual | G15: 21281 | H15: 0.05 | I15: =G15*H15 | J15: =G15-I15 | K15: 0.18 | L15: =J15*K15 | M15: =J15+L15 | N15: Cash | O15: Pending
A16: 45685 | B16: INV-2025-1015 | C16: Manoj Das | D16: Regular Cleaning | E16: Commercial | F16: Tech Park | G16: 119592 | H16: 0 | I16: =G16*H16 | J16: =G16-I16 | K16: 0.18 | L16: =J16*K16 | M16: =J16+L16 | N16: Cash | O16: Pending

Sheet Expense Tracker
A1: Date | B1: Expense ID | C1: Category | D1: Description | E1: Vendor/Payee | F1: Base Amount (₹) | G1: GST % | H1: GST Amount (₹) | I1: Total Amount (₹) | J1: Payment Mode | K1: Payment Status | L1: Notes
A2: 45665 | B2: EXP-2025-101 | C2: Miscellaneous | D2: Misc Purchase | E2: City Fuel Station | F2: 3173 | G2: 0.18 | H2: =F2*G2 | I2: =F2+H2 | J2: Card | K2: Pending
A3: 45662 | B3: EXP-2025-102 | C3: Miscellaneous | D3: Office Supplies | E3: Google Ads | F3: 920 | G3: 0.18 | H3: =F3*G3 | I3: =F3+H3 | J3: Cash | K3: Pending
A4: 45680 | B4: EXP-2025-103 | C4: Travel & Fuel | D4: Petrol/Diesel | E4: City Fuel Station | F4: 761 | G4: 0.18 | H4: =F4*G4 | I4: =F4+H4 | J4: Cash | K4: Pending
A5: 45671 | B5: EXP-2025-104 | C5: Vendor Payment | D5: Misc Purchase | E5: Facebook Ads | F5: 1828 | G5: 0.18 | H5: =F5*G5 | I5: =F5+H5 | J5: UPI | K5: Pending
A6: 45680 | B6: EXP-2025-105 | C6: Travel & Fuel | D6: Petrol/Diesel | E6: City Fuel Station | F6: 2442 | G6: 0.18 | H6: =F6*G6 | I6: =F6+H6 | J6: Cash | K6: Received
A7: 45685 | B7: EXP-2025-106 | C7: Travel & Fuel | D7: Petrol/Diesel | E7: City Fuel Station | F7: 631 | G7: 0.18 | H7: =F7*G7 | I7: =F7+H7 | J7: Cash | K7: Pending
A8: 45670 | B8: EXP-2025-107 | C8: Vendor Payment | D8: Utility Bill | E8: City Fuel Station | F8: 4177 | G8: 0.18 | H8: =F8*G8 | I8: =F8+H8 | J8: Cash | K8: Pending
A9: 45674 | B9: EXP-2025-108 | C9: Travel & Fuel | D9: Petrol/Diesel | E9: City Fuel Station | F9: 1549 | G9: 0.18 | H9: =F9*G9 | I9: =F9+H9 | J9: Bank Transfer | K9: Received
A10: 45670 | B10: EXP-2025-109 | C10: Office Expenses | D10: Misc Purchase | E10: City Fuel Station | F10: 3235 | G10: 0.18 | H10: =F10*G10 | I10: =F10+H10 | J10: Cash | K10: Received
A11: 45684 | B11: EXP-2025-110 | C11: Miscellaneous | D11: Misc Purchase | E11: Facebook Ads | F11: 1750 | G11: 0.18 | H11: =F11*G11 | I11: =F11+H11 | J11: Card | K11: Pending
A12: 45682 | B12: EXP-2025-111 | C12: Marketing | D12: Facebook Ads | E12: Facebook Ads | F12: 11608 | G12: 0.18 | H12: =F12*G12 | I12: =F12+H12 | J12: Card | K12: Pending
A13: 45674 | B13: EXP-2025-112 | C13: Miscellaneous | D13: Misc Purchase | E13: Office Depot | F13: 2018 | G13: 0.18 | H13: =F13*G13 | I13: =F13+H13 | J13: Cash | K13: Received
... A16: 45675 | B16: EXP-2025-115 | C16: Office Expenses | D16: Office Supplies | E16: Google Ads | F16: 2451 | G16: 0.18 | H16: =F16*G16 | I16: =F16+H16 | J16: Card | K16: Pending

Sheet Employee Salaries
A1: Month | B1: Employee ID | C1: Employee Name | D1: Designation | E1: Department | F1: Basic Salary (₹) | G1: HRA (₹) | H1: Other Allowances (₹) | I1: Gross Salary (₹) | J1: PF Deduction (₹) | K1: ESI Deduction (₹) | L1: Other Deductions (₹) | M1: Total Deductions (₹) | N1: Net Salary (₹) | O1: Payment Date | P1: Payment Mode | Q1: Payment Status | R1: Notes
A2: January 2025 | B2: EMP001 | C2: Ramesh Kumar | D2: Driver | E2: Operations | F2: 18000 | G2: 0 | H2: 0 | I2: =F2+G2+H2 | J2: 0 | K2: 0 | L2: 0 | M2: =J2+K2+L2 | N2: =I2-M2 | O2: 45688 | P2: Bank Transfer | Q2: Paid
A3: January 2025 | B3: EMP002 | C3: Suresh Nair | D3: Technician | E3: Operations | F3: 22000 | G3: 0 | H3: 0 | I3: =F3+G3+H3 | J3: 0 | K3: 0 | L3: 0 | M3: =J3+K3+L3 | N3: =I3-M3 | O3: 45688 | P3: Bank Transfer | Q3: Paid
A4: January 2025 | B4: EMP003 | C4: Anil Sharma | D4: Helper | E4: Operations | F4: 15000 | G4: 0 | H4: 0 | I4: =F4+G4+H4 | J4: 0 | K4: 0 | L4: 0 | M4: =J4+K4+L4 | N4: =I4-M4 | O4: 45688 | P4: Bank Transfer | Q4: Paid
A5: January 2025 | B5: EMP004 | C5: Priya Menon | D5: Supervisor | E5: Operations | F5: 28000 | G5: 0 | H5: 0 | I5: =F5+G5+H5 | J5: 0 | K5: 0 | L5: 0 | M5: =J5+K5+L5 | N5: =I5-M5 | O5: 45688 | P5: Bank Transfer | Q5: Paid
A6: January 2025 | B6: EMP005 | C6: Karthik Reddy | D6: Technician | E6: Operations | F6: 22000 | G6: 0 | H6: 0 | I6: =F6+G6+H6 | J6: 0 | K6: 0 | L6: 0 | M6: =J6+K6+L6 | N6: =I6-M6 | O6: 45688 | P6: Bank Transfer | Q6: Paid
A7: January 2025 | B7: EMP006 | C7: Lakshmi Iyer | D7: Admin | E7: Office | F7: 20000 | G7: 0 | H7: 0 | I7: =F7+G7+H7 | J7: 0 | K7: 0 | L7: 0 | M7: =J7+K7+L7 | N7: =I7-M7 | O7: 45688 | P7: Bank Transfer | Q7: Paid
A8: January 2025 | B8: EMP007 | C8: Vijay Das | D8: Helper | E8: Operations | F8: 15000 | G8: 0 | H8: 0 | I8: =F8+G8+H8 | J8: 0 | K8: 0 | L8: 0 | M8: =J8+K8+L8 | N8: =I8-M8 | O8: 45688 | P8: Bank Transfer | Q8: Paid
A9: January 2025 | B9: EMP008 | C9: Meena Pillai | D9: Accounts | E9: Office | F9: 25000 | G9: 0 | H9: 0 | I9: =F9+G9+H9 | J9: 0 | K9: 0 | L9: 0 | M9: =J9+K9+L9 | N9: =I9-M9 | O9: 45688 | P9: Bank Transfer | Q9: Paid

Sheet Contractor Payments
A1: Date | B1: Payment ID | C1: Contractor Name | D1: Contractor PAN | E1: Service Type | F1: Project/Work Description | G1: Gross Amount (₹) | H1: TDS % (Sec 194C) | I1: TDS Amount (₹) | J1: Net Payable (₹) | K1: Payment Date | L1: Payment Mode | M1: Payment Status | N1: TDS Deposited | O1: Notes
A2: 45673 | B2: CONT-2025-301 | C2: Sharma Cleaning Services | D2: ABCPS1234A | E2: Deep Cleaning | F2: Green Valley Phase 1 | G2: 45000 | H2: 0.02 | I2: =G2*H2 | J2: =G2-I2 | K2: 45664 | L2: Cheque | M2: Pending | N2: Yes
A3: 45686 | B3: CONT-2025-302 | C3: Krishna Pest Control | D3: DEFPK5678B | E3: Pest Control | F3: Tech Park Building A | G3: 35000 | H3: 0.02 | I3: =G3*H3 | J3: =G3-I3 | K3: 45675 | L3: UPI | M3: Pending | N3: No
A4: 45670 | B4: CONT-2025-303 | C4: Apex Painting Works | D4: GHIPA9012C | E4: Painting | F4: Residential Complex | G4: 85000 | H4: 0.02 | I4: =G4*H4 | J4: =G4-I4 | K4: 45681 | L4: Cheque | M4: Paid | N4: Yes
A5: 45686 | B5: CONT-2025-304 | C5: City Plumbers | D5: JKLPC3456D | E5: Plumbing | F5: Apartment Maintenance | G5: 28000 | H5: 0.01 | I5: =G5*H5 | J5: =G5-I5 | K5: 45668 | L5: UPI | M5: Paid | N5: No
A6: 45658 | B6: CONT-2025-305 | C6: Royal AC Services | D6: MNOPR7890E | E6: AC Service | F6: Office Complex | G6: 42000 | H6: 0.02 | I6: =G6*H6 | J6: =G6-I6 | K6: 45687 | L6: Cheque | M6: Pending | N6: No
A7: 45674 | B7: CONT-2025-306 | C7: Metro Electrical | D7: PQRME1234F | E7: Electrical | F7: New Installation | G7: 55000 | H7: 0.02 | I7: =G7*H7 | J7: =G7-I7 | K7: 45666 | L7: Cheque | M7: Paid | N7: No
A8: 45661 | B8: CONT-2025-307 | C8: Clean Pro Services | D8: STUCL5678G | E8: Regular Cleaning | F8: Monthly Contract | G8: 65000 | H8: 0.02 | I8: =G8*H8 | J8: =G8-I8 | K8: 45682 | L8: Bank Transfer | M8: Pending | N8: Yes
A9: 45659 | B9: CONT-2025-308 | C9: Pest Masters | D9: VWXPM9012H | E9: Pest Control | F9: Quarterly Treatment | G9: 48000 | H9: 0.02 | I9: =G9*H9 | J9: =G9-I9 | K9: 45678 | L9: Bank Transfer | M9: Paid | N9: No

Sheet Stock Purchases
A1: Date | B1: Purchase ID | C1: Vendor Name | D1: Vendor GSTIN | E1: Invoice No | F1: Item Type | G1: Item Name | H1: Quantity | I1: Unit | J1: Rate (₹) | K1: Base Amount (₹) | L1: GST % | M1: GST Amount (₹) | N1: Total Amount (₹) | O1: Payment Status | P1: Notes
A2: 45681 | B2: PO-2025-201 | C2: City Supplies | D2: 29AABCS5678B2ZW | E2: INV/7224 | F2: Chemical | G2: Floor Cleaner | H2: 55 | I2: Liters | J2: 120 | K2: =H2*J2 | L2: 0.18 | M2: =K2*L2 | N2: =K2+M2 | O2: Pending
A3: 45667 | B3: PO-2025-202 | C3: Kumar Chemicals Pvt Ltd | D3: 29AABCK1234A1ZV | E3: INV/6650 | F3: Chemical | G3: Floor Cleaner | H3: 28 | I3: Liters | J3: 120 | K3: =H3*J3 | L3: 0.18 | M3: =K3*L3 | N3: =K3+M3 | O3: Pending
A4: 45665 | B4: PO-2025-203 | C4: Kumar Chemicals Pvt Ltd | D4: 29AABCK1234A1ZV | E4: INV/3241 | F4: Accessory | G4: Rubber Gloves | H4: 46 | I4: Pairs | J4: 45 | K4: =H4*J4 | L4: 0.18 | M4: =K4*L4 | N4: =K4+M4 | O4: Pending
A5: 45672 | B5: PO-2025-204 | C5: Kumar Chemicals Pvt Ltd | D5: 29AABCK1234A1ZV | E5: INV/4657 | F5: Chemical | G5: Surface Disinfectant | H5: 88 | I5: Liters | J5: 180 | K5: =H5*J5 | L5: 0.18 | M5: =K5*L5 | N5: =K5+M5 | O5: Paid
A6: 45660 | B6: PO-2025-205 | C6: Metro Cleaning Supplies | D6: 29AABCM9012C3ZX | E6: INV/3582 | F6: Chemical | G6: Glass Cleaner | H6: 38 | I6: Liters | J6: 95 | K6: =H6*J6 | L6: 0.18 | M6: =K6*L6 | N6: =K6+M6 | O6: Pending
A7: 45662 | B7: PO-2025-206 | C7: Metro Cleaning Supplies | D7: 29AABCM9012C3ZX | E7: INV/1468 | F7: Chemical | G7: Floor Cleaner | H7: 13 | I7: Liters | J7: 120 | K7: =H7*J7 | L7: 0.18 | M7: =K7*L7 | N7: =K7+M7 | O7: Pending
A8: 45661 | B8: PO-2025-207 | C8: Kumar Chemicals Pvt Ltd | D8: 29AABCK1234A1ZV | E8: INV/8637 | F8: Accessory | G8: Microfiber Cloth | H8: 66 | I8: Pieces | J8: 80 | K8: =H8*J8 | L8: 0.18 | M8: =K8*L8 | N8: =K8+M8 | O8: Paid
A9: 45665 | B9: PO-2025-208 | C9: City Supplies | D9: 29AABCS5678B2ZW | E9: INV/8959 | F9: Chemical | G9: Glass Cleaner | H9: 72 | I9: Liters | J9: 95 | K9: =H9*J9 | L9: 0.18 | M9: =K9*L9 | N9: =K9+M9 | O9: Paid
A10: 45667 | B10: PO-2025-209 | C10: Metro Cleaning Supplies | D10: 29AABCM9012C3ZX | E10: INV/6432 | F10: Accessory | G10: Microfiber Cloth | H10: 39 | I10: Pieces | J10: 80 | K10: =H10*J10 | L10: 0.18 | M10: =K10*L10 | N10: =K10+M10 | O10: Pending
A11: 45676 | B11: PO-2025-210 | C11: City Supplies | D11: 29AABCS5678B2ZW | E11: INV/3106 | F11: Accessory | G11: Microfiber Cloth | H11: 18 | I11: Pieces | J11: 80 | K11: =H11*J11 | L11: 0.18 | M11: =K11*L11 | N11: =K11+M11 | O11: Paid

Sheet Machines & Equipment
A1: Machine ID | B1: Machine Name | C1: Model | D1: Category | E1: Purchase Date | F1: Purchase Invoice No | G1: Vendor GST No | H1: Base Cost (₹) | I1: GST % | J1: GST Amount (₹) | K1: Total Cost (₹) | L1: Current Status | M1: Location | N1: Notes
A2: M001 | B2: Floor Scrubber | C2: Karcher BD 50/50 | D2: Cleaning Machine | E2: 45000 | F2: INV/K/2023/1234 | G2: 29AABCK1234A1Z5 | H2: 72034 | I2: 0.18 | J2: =H2*I2 | K2: =H2+J2 | L2: Active | M2: Team A
A3: M002 | B3: Pressure Washer | C3: Bosch AQT 45-14X | D3: Cleaning Machine | E3: 45066 | F3: INV/B/2023/5678 | G3: 29AABCB5678B2Z6 | H3: 38136 | I3: 0.18 | J3: =H3*I3 | K3: =H3+J3 | L3: Active | M3: Team B
A4: M003 | B4: Vacuum Cleaner | C4: Eureka Forbes Pro | D4: Cleaning Machine | E4: 44783 | F4: INV/E/2022/9012 | G4: 29AABCE9012C3Z7 | H4: 23729 | I4: 0.18 | J4: =H4*I4 | K4: =H4+J4 | L4: Active | M4: Team A
A5: M004 | B5: Pest Control Sprayer | C5: Solo 475 | D5: Spray Equipment | E5: 44931 | F5: INV/S/2023/3456 | G5: 29AABCS3456D4Z8 | H5: 12712 | I5: 0.18 | J5: =H5*I5 | K5: =H5+J5 | L5: Active | M5: Pest Team
A6: M005 | B6: Paint Sprayer | C6: Graco Magnum X5 | D6: Spray Equipment | E6: 45119 | F6: INV/G/2023/7890 | G6: 29AABCG7890E5Z9 | H6: 55085 | I6: 0.18 | J6: =H6*I6 | K6: =H6+J6 | L6: Under Repair | M6: Painting
A7: M006 | B7: Drill Machine | C7: Bosch GSB 600 | D7: Power Tools | E7: 44669 | F7: INV/B/2022/1111 | G7: 29AABCB5678B2Z6 | H7: 7203 | I7: 0.18 | J7: =H7*I7 | K7: =H7+J7 | L7: Active | M7: General
A8: M007 | B8: Angle Grinder | C8: Makita GA4030 | D8: Power Tools | E8: 44979 | F8: INV/M/2023/2222 | G8: 29AABCM2222F6Z0 | H8: 5508 | I8: 0.18 | J8: =H8*I8 | K8: =H8+J8 | L8: Active | M8: General
A9: M008 | B9: Steam Cleaner | C9: Karcher SC3 | D9: Cleaning Machine | E9: 45299 | F9: INV/K/2024/3333 | G9: 29AABCK1234A1Z5 | H9: 29661 | I9: 0.18 | J9: =H9*I9 | K9: =H9+J9 | L9: Active | M9: Team C

Sheet Machine Maintenance
A1: Date | B1: Machine ID | C1: Machine Name | D1: Maintenance Type | E1: Description | F1: Base Cost (₹) | G1: GST % | H1: GST Amount (₹) | I1: Total Cost (₹) | J1: Done By | K1: Next Service | L1: Service Status | M1: Notes
A2: 45505 | B2: M001 | C2: Floor Scrubber | D2: Service | E2: Brush replacement | F2: 3814 | G2: 0.18 | H2: =F2*G2 | I2: =F2+H2 | J2: Karcher Service | K2: 45689 | L2: Service Completed
A3: 45540 | B3: M002 | C3: Pressure Washer | D3: Repair | E3: Nozzle fixed | F3: 1525 | G3: 0.18 | H3: =F3*G3 | I3: =F3+H3 | J3: Bosch Service | K3: 45721 | L3: Service Completed
A4: 45575 | B4: M003 | C4: Vacuum Cleaner | D4: Service | E4: Filter cleaning | F4: 678 | G4: 0.18 | H4: =F4*G4 | I4: =F4+H4 | J4: In-house | K4: 45757 | L4: Service Completed
A5: 45611 | B5: M005 | C5: Paint Sprayer | D5: Repair | E5: Motor rewinding | F5: 7203 | G5: 0.18 | H5: =F5*G5 | I5: =F5+H5 | J5: Graco Service | K5: 45792 | L5: Out for Service
A6: 45662 | B6: M004 | C6: Pest Sprayer | D6: Service | E6: Valve check | F6: 424 | G6: 0.18 | H6: =F6*G6 | I6: =F6+H6 | J6: In-house | K6: 45843 | L6: Service Completed

Sheet Chemicals Stock
A1: Item ID | B1: Chemical Name | C1: Brand | D1: Category | E1: Unit | F1: Opening Stock | G1: Stock Added | H1: Stock Used | I1: Closing Stock | J1: Min Level | K1: Status | L1: Last Updated
A2: CH001 | B2: Floor Cleaner | C2: Lizol | D2: Cleaning Agents | E2: Liters | F2: 50 | G2: 100 | H2: 80 | I2: =F2+G2-H2 | J2: 20 | K2: =IF(I2<J2,"Low Stock","OK") | L2: 45682
A3: CH002 | B3: Glass Cleaner | C3: Colin | D3: Cleaning Agents | E3: Liters | F3: 30 | G3: 50 | H3: 45 | I3: =F3+G3-H3 | J3: 15 | K3: =IF(I3<J3,"Low Stock","OK") | L3: 45682
A4: CH003 | B4: Toilet Cleaner | C4: Harpic | D4: Cleaning Agents | E4: Liters | F4: 40 | G4: 80 | H4: 70 | I4: =F4+G4-H4 | J4: 20 | K4: =IF(I4<J4,"Low Stock","OK") | L4: 45682
A5: CH004 | B5: Pesticide Spray | C5: Baygon Pro | D5: Pest Control | E5: Cans | F5: 25 | G5: 50 | H5: 40 | I5: =F5+G5-H5 | J5: 10 | K5: =IF(I5<J5,"Low Stock","OK") | L5: 45682
A6: CH005 | B6: Surface Disinfectant | C6: Lysol | D6: Sanitizers | E6: Liters | F6: 25 | G6: 50 | H6: 40 | I6: =F6+G6-H6 | J6: 15 | K6: =IF(I6<J6,"Low Stock","OK") | L6: 45682

Sheet Accessories Stock
A1: Item ID | B1: Item Name | C1: Category | D1: Unit | E1: Opening Stock | F1: Stock Added | G1: Stock Used | H1: Closing Stock | I1: Min Level | J1: Status | K1: Last Updated
A2: AC001 | B2: Rubber Hose (10m) | C2: Pipes & Hoses | D2: Pieces | E2: 10 | F2: 15 | G2: 12 | H2: =E2+F2-G2 | I2: 5 | J2: =IF(H2<I2,"Low Stock","OK") | K2: 45682
A3: AC002 | B3: Floor Mop | C3: Brushes & Mops | D3: Pieces | E3: 20 | F3: 30 | G3: 25 | H3: =E3+F3-G3 | I3: 10 | J3: =IF(H3<I3,"Low Stock","OK") | K3: 45682
A4: AC003 | B4: Microfiber Cloth | C4: Cloths & Wipes | D4: Pieces | E4: 50 | F4: 100 | G4: 80 | H4: =E4+F4-G4 | I4: 25 | J4: =IF(H4<I4,"Low Stock","OK") | K4: 45682
A5: AC004 | B5: Rubber Gloves | C5: Gloves & Safety | D5: Pairs | E5: 30 | F5: 50 | G5: 40 | H5: =E5+F5-G5 | I5: 15 | J5: =IF(H5<I5,"Low Stock","OK") | K5: 45682
A6: AC005 | B6: Spray Bottles | C6: Other | D6: Pieces | E6: 20 | F6: 30 | G6: 22 | H6: =E6+F6-G6 | I6: 10 | J6: =IF(H6<I6,"Low Stock","OK") | K6: 45682

Sheet Stock Transactions
A1: Date | B1: Transaction ID | C1: Item Type | D1: Item ID | E1: Item Name | F1: Transaction Type | G1: Quantity | H1: Unit Rate (₹) | I1: GST % | J1: GST Amount (₹) | K1: Total Cost (₹) | L1: Project/Team | M1: Notes
A2: 45659 | B2: TXN001 | C2: Chemical | D2: CH001 | E2: Floor Cleaner | F2: Purchase | G2: 50 | H2: 120 | I2: 0.18 | J2: =G2*H2*I2 | K2: =G2*H2+J2 | L2: Warehouse
A3: 45662 | B3: TXN002 | C3: Accessory | D3: AC003 | E3: Microfiber Cloth | F3: Purchase | G3: 50 | H3: 80 | I3: 0.18 | J3: =G3*H3*I3 | K3: =G3*H3+J3 | L3: Warehouse
A4: 45663 | B4: TXN003 | C4: Chemical | D4: CH001 | E4: Floor Cleaner | F4: Used | G4: 20 | H4: 0 | I4: 0 | J4: =G4*H4*I4 | K4: =G4*H4+J4 | L4: Team A
A5: 45665 | B5: TXN004 | C5: Accessory | D5: AC004 | E5: Rubber Gloves | F5: Used | G5: 10 | H5: 0 | I5: 0 | J5: =G5*H5*I5 | K5: =G5*H5+J5 | L5: Team B
A6: 45667 | B6: TXN005 | C6: Chemical | D6: CH002 | E6: Glass Cleaner | F6: Purchase | G6: 25 | H6: 95 | I6: 0.18 | J6: =G6*H6*I6 | K6: =G6*H6+J6 | L6: Warehouse

Sheet Income Summary
A1: INCOME SUMMARY REPORT
A3: SERVICE-WISE REVENUE
A4: Service Type | B4: Base Revenue (₹) | C4: Discount (₹) | D4: GST Collected (₹) | E4: Total Revenue (₹) | F4: Orders
A5: Deep Cleaning | B5: =SUMIF('Income Tracker'!D:D,A5,'Income Tracker'!G:G) | C5: =SUMIF('Income Tracker'!D:D,A5,'Income Tracker'!I:I) | D5: =SUMIF('Income Tracker'!D:D,A5,'Income Tracker'!L:L) | E5: =SUMIF('Income Tracker'!D:D,A5,'Income Tracker'!M:M) | F5: =COUNTIF('Income Tracker'!D:D,A5)
A6: Regular Cleaning | B6: =SUMIF('Income Tracker'!D:D,A6,'Income Tracker'!G:G) | C6: =SUMIF('Income Tracker'!D:D,A6,'Income Tracker'!I:I) | D6: =SUMIF('Income Tracker'!D:D,A6,'Income Tracker'!L:L) | E6: =SUMIF('Income Tracker'!D:D,A6,'Income Tracker'!M:M) | F6: =COUNTIF('Income Tracker'!D:D,A6)
A7: Pest Control | B7: =SUMIF('Income Tracker'!D:D,A7,'Income Tracker'!G:G) | C7: =SUMIF('Income Tracker'!D:D,A7,'Income Tracker'!I:I) | D7: =SUMIF('Income Tracker'!D:D,A7,'Income Tracker'!L:L) | E7: =SUMIF('Income Tracker'!D:D,A7,'Income Tracker'!M:M) | F7: =COUNTIF('Income Tracker'!D:D,A7)
A8: Painting | B8: =SUMIF('Income Tracker'!D:D,A8,'Income Tracker'!G:G) | C8: =SUMIF('Income Tracker'!D:D,A8,'Income Tracker'!I:I) | D8: =SUMIF('Income Tracker'!D:D,A8,'Income Tracker'!L:L) | E8: =SUMIF('Income Tracker'!D:D,A8,'Income Tracker'!M:M) | F8: =COUNTIF('Income Tracker'!D:D,A8)
A9: Plumbing | B9: =SUMIF('Income Tracker'!D:D,A9,'Income Tracker'!G:G) | C9: =SUMIF('Income Tracker'!D:D,A9,'Income Tracker'!I:I) | D9: =SUMIF('Income Tracker'!D:D,A9,'Income Tracker'!L:L) | E9: =SUMIF('Income Tracker'!D:D,A9,'Income Tracker'!M:M) | F9: =COUNTIF('Income Tracker'!D:D,A9)
A10: Electrical | B10: =SUMIF('Income Tracker'!D:D,A10,'Income Tracker'!G:G) | C10: =SUMIF('Income Tracker'!D:D,A10,'Income Tracker'!I:I) | D10: =SUMIF('Income Tracker'!D:D,A10,'Income Tracker'!L:L) | E10: =SUMIF('Income Tracker'!D:D,A10,'Income Tracker'!M:M) | F10: =COUNTIF('Income Tracker'!D:D,A10)
A11: Carpentry | B11: =SUMIF('Income Tracker'!D:D,A11,'Income Tracker'!G:G) | C11: =SUMIF('Income Tracker'!D:D,A11,'Income Tracker'!I:I) | D11: =SUMIF('Income Tracker'!D:D,A11,'Income Tracker'!L:L) | E11: =SUMIF('Income Tracker'!D:D,A11,'Income Tracker'!M:M) | F11: =COUNTIF('Income Tracker'!D:D,A11)
A12: AC Service | B12: =SUMIF('Income Tracker'!D:D,A12,'Income Tracker'!G:G) | C12: =SUMIF('Income Tracker'!D:D,A12,'Income Tracker'!I:I) | D12: =SUMIF('Income Tracker'!D:D,A12,'Income Tracker'!L:L) | E12: =SUMIF('Income Tracker'!D:D,A12,'Income Tracker'!M:M) | F12: =COUNTIF('Income Tracker'!D:D,A12)
A13: TOTAL | B13: =SUM(B5:B12) | C13: =SUM(C5:C12) | D13: =SUM(D5:D12) | E13: =SUM(E5:E12) | F13: =SUM(F5:F12)

Sheet Expense Summary
A1: EXPENSE SUMMARY REPORT
A3: CATEGORY-WISE EXPENSES
A4: Category | B4: Base Amount (₹) | C4: GST Paid (₹) | D4: Total Amount (₹) | E4: Count
A5: Vendor Payment | B5: =SUMIF('Expense Tracker'!C:C,A5,'Expense Tracker'!F:F) | C5: =SUMIF('Expense Tracker'!C:C,A5,'Expense Tracker'!H:H) | D5: =SUMIF('Expense Tracker'!C:C,A5,'Expense Tracker'!I:I) | E5: =COUNTIF('Expense Tracker'!C:C,A5)
A6: Travel & Fuel | B6: =SUMIF('Expense Tracker'!C:C,A6,'Expense Tracker'!F:F) | C6: =SUMIF('Expense Tracker'!C:C,A6,'Expense Tracker'!H:H) | D6: =SUMIF('Expense Tracker'!C:C,A6,'Expense Tracker'!I:I) | E6: =COUNTIF('Expense Tracker'!C:C,A6)
A7: Marketing | B7: =SUMIF('Expense Tracker'!C:C,A7,'Expense Tracker'!F:F) | C7: =SUMIF('Expense Tracker'!C:C,A7,'Expense Tracker'!H:H) | D7: =SUMIF('Expense Tracker'!C:C,A7,'Expense Tracker'!I:I) | E7: =COUNTIF('Expense Tracker'!C:C,A7)
A8: Office Expenses | B8: =SUMIF('Expense Tracker'!C:C,A8,'Expense Tracker'!F:F) | C8: =SUMIF('Expense Tracker'!C:C,A8,'Expense Tracker'!H:H) | D8: =SUMIF('Expense Tracker'!C:C,A8,'Expense Tracker'!I:I) | E8: =COUNTIF('Expense Tracker'!C:C,A8)
A9: Miscellaneous | B9: =SUMIF('Expense Tracker'!C:C,A9,'Expense Tracker'!F:F) | C9: =SUMIF('Expense Tracker'!C:C,A9,'Expense Tracker'!H:H) | D9: =SUMIF('Expense Tracker'!C:C,A9,'Expense Tracker'!I:I) | E9: =COUNTIF('Expense Tracker'!C:C,A9)
A10: TOTAL | B10: =SUM(B5:B9) | C10: =SUM(C5:C9) | D10: =SUM(D5:D9) | E10: =SUM(E5:E9)

Sheet GST Summary
A1: GST SUMMARY REPORT
A3: GST COLLECTED (OUTPUT TAX)
A4: Source | B4: Base Amount (₹) | C4: GST Amount (₹)
A5: Service Revenue | B5: =SUM('Income Tracker'!J:J) | C5: =SUM('Income Tracker'!L:L)
A6: TOTAL GST COLLECTED | B6: =B5 | C6: =C5
A9: GST PAID (INPUT TAX)
A10: Source | B10: Base Amount (₹) | C10: GST Amount (₹)
A11: Expenses | B11: =SUM('Expense Tracker'!F:F) | C11: =SUM('Expense Tracker'!H:H)
A12: Stock Purchases | B12: =SUM('Stock Purchases'!K:K) | C12: =SUM('Stock Purchases'!M:M)
A13: Machine Purchases | B13: =SUM('Machines & Equipment'!H:H) | C13: =SUM('Machines & Equipment'!J:J)
A14: Maintenance | B14: =SUM('Machine Maintenance'!F:F) | C14: =SUM('Machine Maintenance'!H:H)
A15: TOTAL GST PAID | B15: =SUM(B11:B14) | C15: =SUM(C11:C14)
A18: NET GST PAYABLE | C18: =C6-C15

Sheet TDS Summary
A1: TDS SUMMARY REPORT
A2: (For TDS Filing - Section 194C)
A4: TDS DEDUCTED FROM CONTRACTORS
A5: Metric | B5: Amount (₹)
A6: Total Contractor Payments (Gross) | B6: =SUM('Contractor Payments'!G:G)
A7: Total TDS Deducted | B7: =SUM('Contractor Payments'!I:I)
A8: Total Net Paid to Contractors | B8: =SUM('Contractor Payments'!J:J)
A9: TDS Deposited | B9: =SUMIF('Contractor Payments'!N:N,"Yes",'Contractor Payments'!I:I)
A10: TDS Pending Deposit | B10: =B7-B9

Sheet Profitability Report
A1: PROFITABILITY ANALYSIS
A3: ACTUAL NET PROFIT CALCULATION
A4: Description | B4: Amount (₹)
A5: TOTAL REVENUE (After Discount, excl. GST) | B5: =SUM('Income Tracker'!J:J)
A7: Less: Operating Expenses | B7: =SUM('Expense Tracker'!F:F)
A8: Less: Employee Salaries | B8: =SUM('Employee Salaries'!N:N)
A9: Less: Contractor Payments | B9: =SUM('Contractor Payments'!J:J)
A10: Less: Stock Purchases | B10: =SUM('Stock Purchases'!K:K)
A11: Less: Machine Maintenance | B11: =SUM('Machine Maintenance'!F:F)
A13: TOTAL EXPENSES | B13: =B6+B7+B8+B9+B10
A15: NET PROFIT / (LOSS) | B15: =B5-B12
A17: Net Profit Margin % | B17: =IF(B5>0,B14/B5,0)

Sheet Stock Reports
A1: STOCK & INVENTORY REPORTS
A3: ASSET VALUE SUMMARY
A4: Category | B4: Base Value (₹) | C4: GST (₹) | D4: Total (₹)
A5: Cleaning Machine | B5: =SUMIF('Machines & Equipment'!D:D,A5,'Machines & Equipment'!H:H) | C5: =SUMIF('Machines & Equipment'!D:D,A5,'Machines & Equipment'!J:J) | D5: =SUMIF('Machines & Equipment'!D:D,A5,'Machines & Equipment'!K:K)
A6: Spray Equipment | B6: =SUMIF('Machines & Equipment'!D:D,A6,'Machines & Equipment'!H:H) | C6: =SUMIF('Machines & Equipment'!D:D,A6,'Machines & Equipment'!J:J) | D6: =SUMIF('Machines & Equipment'!D:D,A6,'Machines & Equipment'!K:K)
A7: Power Tools | B7: =SUMIF('Machines & Equipment'!D:D,A7,'Machines & Equipment'!H:H) | C7: =SUMIF('Machines & Equipment'!D:D,A7,'Machines & Equipment'!J:J) | D7: =SUMIF('Machines & Equipment'!D:D,A7,'Machines & Equipment'!K:K)
A8: Safety Equipment | B8: =SUMIF('Machines & Equipment'!D:D,A8,'Machines & Equipment'!H:H) | C8: =SUMIF('Machines & Equipment'!D:D,A8,'Machines & Equipment'!J:J) | D8: =SUMIF('Machines & Equipment'!D:D,A8,'Machines & Equipment'!K:K)
A9: TOTAL | B9: =SUM(B5:B8) | C9: =SUM(C5:C8) | D9: =SUM(D5:D8)

Sheet Dashboard
A1: MIS DASHBOARD
A3: KEY FINANCIAL METRICS
A5: TOTAL REVENUE | C5: TOTAL EXPENSES | E5: NET PROFIT | G5: PROFIT MARGIN
A6: =SUM('Income Tracker'!M:M) | C6: =SUM('Expense Tracker'!I:I)+SUM('Employee Salaries'!N:N)+SUM('Contractor Payments'!J:J)+SUM('Stock Purchases'!N:N)+SUM('Machine Maintenance'!I:I) | E6: =SUM('Income Tracker'!J:J)-SUM('Expense Tracker'!F:F)-SUM('Employee Salaries'!N:N)-SUM('Contractor Payments'!J:J)-SUM('Stock Purchases'!K:K)-SUM('Machine Maintenance'!F:F) | G6: =IF(SUM('Income Tracker'!J:J)>0,E6/SUM('Income Tracker'!J:J),0)
A8: EXPENSE BREAKDOWN | D8: TAX SUMMARY | G8: PAYROLL SUMMARY
A9: Expense Type | B9: Amount (₹) | D9: Tax Type | E9: Amount (₹) | G9: Metric | H9: Amount (₹)
A10: Operating Expenses | B10: =SUM('Expense Tracker'!I:I) | D10: GST Collected | E10: =SUM('Income Tracker'!L:L) | G10: Total Gross Salary | H10: =SUM('Employee Salaries'!I:I)
A11: Employee Salaries | B11: =SUM('Employee Salaries'!N:N) | D11: GST Paid | E11: =SUM('Expense Tracker'!H:H)+SUM('Stock Purchases'!M:M)+SUM('Machine Maintenance'!H:H) | G11: Total PF Deduction | H11: =SUM('Employee Salaries'!J:J)
A12: Contractor Payments | B12: =SUM('Contractor Payments'!J:J) | D12: Net GST Payable | E12: =E10-E11 | G12: Total ESI Deduction | H12: =SUM('Employee Salaries'!K:K)
A13: Stock Purchases | B13: =SUM('Stock Purchases'!N:N) | D13: TDS Deducted | E13: =SUM('Contractor Payments'!I:I) | G13: Total Net Salary Paid | H13: =SUM('Employee Salaries'!N:N)
A14: Machine Maintenance | B14: =SUM('Machine Maintenance'!I:I) | D14: TDS Pending Deposit | E14: =SUM('Contractor Payments'!I:I)-SUMIF('Contractor Payments'!N:N,"Yes",'Contractor Payments'!I:I) | G14: Total Employees | H14: =COUNTA('Employee Salaries'!B:B)-1
A15: TOTAL | B15: =SUM(B10:B14)
A18: Service | B18: Revenue
A19: Deep Cleaning | B19: =SUMIF('Income Tracker'!D:D,A19,'Income Tracker'!M:M)
A20: Regular Cleaning | B20: =SUMIF('Income Tracker'!D:D,A20,'Income Tracker'!M:M)
A21: Pest Control | B21: =SUMIF('Income Tracker'!D:D,A21,'Income Tracker'!M:M)
A22: Painting | B22: =SUMIF('Income Tracker'!D:D,A22,'Income Tracker'!M:M)
A23: Plumbing | B23: =SUMIF('Income Tracker'!D:D,A23,'Income Tracker'!M:M)
A24: Electrical | B24: =SUMIF('Income Tracker'!D:D,A24,'Income Tracker'!M:M)
A25: Carpentry | B25: =SUMIF('Income Tracker'!D:D,A25,'Income Tracker'!M:M)
A26: AC Service | B26: =SUMIF('Income Tracker'!D:D,A26,'Income Tracker'!M:M)
