Workbook

Sheet HOW TO USE
A3: SHEET | B3: PURPOSE | C3: HOW TO USE
A4: Income Tracker | B4: Record all service revenue with GST & Discounts | C4: Enter each payment with service type
A5: Expense Tracker | B5: Track all business expenses with GST | C5: Log every expense with category
A6: Employee Salaries | B6: Track employee salary payments | C6: Monthly salary - PF/ESI/HRA default 0
A7: Contractor Payments | B7: Track contractor payouts with TDS | C7: Gross amount, TDS deduction, net payable
A8: Stock Purchases | B8: Track inventory purchases | C8: Vendor purchases with GST
A9: Machines & Equipment | B9: Asset register | C9: Add machines with Invoice & GST details
A10: Machine Maintenance | B10: Track repairs/servicing | C10: Log maintenance with status
A11: Chemicals Stock | B11: Chemical inventory | C11: Track opening, added, used, closing stock
A12: Accessories Stock | B12: Consumables inventory | C12: Track stock levels
A13: Stock Transactions | B13: Stock movement log | C13: Record purchases and usage
A14: GST Invoices | B14: Track GST payments | C14: Invoice-wise GST paid/pending status
... A21: Dashboard | B21: Visual overview | C21: Key metrics with DATE FILTERS

Sheet Income Tracker
A1: Date | B1: Invoice No | C1: Customer Name | D1: Service Type | E1: Project Type | F1: Project Name | G1: Base Amount (₹) | H1: Discount % | I1: Discount Amount (₹) | J1: Amount After Discount (₹) | K1: GST % | L1: GST Amount (₹) | M1: Total Amount (₹) | N1: Payment Mode | O1: Payment Status | P1: Notes
A2: 45658 | B2: INV-2025-1001 | C2: Rajesh Kumar | D2: Carpentry | E2: Individual | G2: 22131 | H2: 0.05 | I2: =G2*H2 | J2: =G2-I2 | K2: 0.18 | L2: =J2*K2 | M2: =J2+L2 | N2: UPI | O2: Pending
A3: 45680 | B3: INV-2025-1002 | C3: Priya Sharma | D3: Painting | E3: Apartment Bulk | F3: Green Valley Apartments | G3: 168243 | H3: 0 | I3: =G3*H3 | J3: =G3-I3 | K3: 0.18 | L3: =J3*K3 | M3: =J3+L3 | N3: Cash | O3: Pending
A4: 45681 | B4: INV-2025-1003 | C4: Amit Patel | D4: AC Service | E4: Individual | G4: 12670 | H4: 0 | I4: =G4*H4 | J4: =G4-I4 | K4: 0.18 | L4: =J4*K4 | M4: =J4+L4 | N4: Cash | O4: Received
A5: 45662 | B5: INV-2025-1004 | C5: Sunita Reddy | D5: Electrical | E5: Apartment Bulk | F5: Green Valley Apartments | G5: 170869 | H5: 0 | I5: =G5*H5 | J5: =G5-I5 | K5: 0.18 | L5: =J5*K5 | M5: =J5+L5 | N5: Cash | O5: Pending
A6: 45663 | B6: INV-2025-1005 | C6: Vikram Singh | D6: Electrical | E6: Apartment Bulk | F6: Green Valley Apartments | G6: 67750 | H6: 0 | I6: =G6*H6 | J6: =G6-I6 | K6: 0.18 | L6: =J6*K6 | M6: =J6+L6 | N6: Card | O6: Received
A7: 45666 | B7: INV-2025-1006 | C7: Deepa Nair | D7: Deep Cleaning | E7: Individual | G7: 12004 | H7: 0 | I7: =G7*H7 | J7: =G7-I7 | K7: 0.18 | L7: =J7*K7 | M7: =J7+L7 | N7: UPI | O7: Pending
A8: 45664 | B8: INV-2025-1007 | C8: Karthik Iyer | D8: Deep Cleaning | E8: Apartment Bulk | F8: Green Valley Apartments | G8: 78098 | H8: 0 | I8: =G8*H8 | J8: =G8-I8 | K8: 0.18 | L8: =J8*K8 | M8: =J8+L8 | N8: UPI | O8: Received
A9: 45667 | B9: INV-2025-1008 | C9: Meena Gupta | D9: Plumbing | E9: Individual | G9: 18298 | H9: 0 | I9: =G9*H9 | J9: =G9-I9 | K9: 0.18 | L9: =J9*K9 | M9: =J9+L9 | N9: UPI | O9: Received
A10: 45676 | B10: INV-2025-1009 | C10: Rahul Verma | D10: Plumbing | E10: Apartment Bulk | F10: Green Valley Apartments | G10: 151520 | H10: 0.05 | I10: =G10*H10 | J10: =G10-I10 | K10: 0.18 | L10: =J10*K10 | M10: =J10+L10 | N10: UPI | O10: Received
A11: 45682 | B11: INV-2025-1010 | C11: Anjali Menon | D11: Pest Control | E11: Apartment Bulk | F11: Green Valley Apartments | G11: 171101 | H11: 0.05 | I11: =G11*H11 | J11: =G11-I11 | K11: 0.18 | L11: =J11*K11 | M11: =J11+L11 | N11: Bank Transfer | O11: Received
A12: 45682 | B12: INV-2025-1011 | C12: Suresh Rao | D12: Carpentry | E12: Apartment Bulk | F12: Green Valley Apartments | G12: 156122 | H12: 0 | I12: =G12*H12 | J12: =G12-I12 | K12: 0.18 | L12: =J12*K12 | M12: =J12+L12 | N12: Bank Transfer | O12: Received
A13: 45660 | B13: INV-2025-1012 | C13: Lakshmi Pillai | D13: Painting | E13: Individual | G13: 22123 | H13: 0 | I13: =G13*H13 | J13: =G13-I13 | K13: 0.18 | L13: =J13*K13 | M13: =J13+L13 | N13: Cash | O13: Pending
A14: 45675 | B14: INV-2025-1013 | C14: Arun Krishnan | D14: AC Service | E14: Apartment Bulk | F14: Green Valley Apartments | G14: 180436 | H14: 0 | I14: =G14*H14 | J14: =G14-I14 | K14: 0.18 | L14: =J14*K14 | M14: =J14+L14 | N14: Bank Transfer | O14: Received
A15: 45679 | B15: INV-2025-1014 | C15: Kavitha Srinivasan | D15: Plumbing | E15: Individual | G15: 24558 | H15: 0 | I15: =G15*H15 | J15: =G15-I15 | K15: 0.18 | L15: =J15*K15 | M15: =J15+L15 | N15: Card | O15: Pending
A16: 45679 | B16: INV-2025-1015 | C16: Manoj Das | D16: Carpentry | E16: Apartment Bulk | F16: Green Valley Apartments | G16: 197777 | H16: 0.05 | I16: =G16*H16 | J16: =G16-I16 | K16: 0.18 | L16: =J16*K16 | M16: =J16+L16 | N16: Cash | O16: Received

Sheet Expense Tracker
A1: Date | B1: Expense ID | C1: Category | D1: Description | E1: Vendor/Payee | F1: Base Amount (₹) | G1: GST % | H1: GST Amount (₹) | I1: Total Amount (₹) | J1: Payment Mode | K1: Payment Status | L1: Notes
A2: 45671 | B2: EXP-2025-101 | C2: Office Expenses | D2: Office Supplies | E2: Facebook Ads | F2: 4528 | G2: 0.18 | H2: =F2*G2 | I2: =F2+H2 | J2: Cash | K2: Pending
A3: 45670 | B3: EXP-2025-102 | C3: Vendor Payment | D3: Utility Bill | E3: City Fuel Station | F3: 2477 | G3: 0.18 | H3: =F3*G3 | I3: =F3+H3 | J3: Bank Transfer | K3: Pending
A4: 45665 | B4: EXP-2025-103 | C4: Travel & Fuel | D4: Petrol/Diesel | E4: City Fuel Station | F4: 1228 | G4: 0.18 | H4: =F4*G4 | I4: =F4+H4 | J4: UPI | K4: Pending
A5: 45683 | B5: EXP-2025-104 | C5: Travel & Fuel | D5: Petrol/Diesel | E5: City Fuel Station | F5: 2677 | G5: 0.18 | H5: =F5*G5 | I5: =F5+H5 | J5: Bank Transfer | K5: Pending
A6: 45664 | B6: EXP-2025-105 | C6: Vendor Payment | D6: Office Supplies | E6: Airtel | F6: 711 | G6: 0.18 | H6: =F6*G6 | I6: =F6+H6 | J6: Cash | K6: Received
A7: 45659 | B7: EXP-2025-106 | C7: Travel & Fuel | D7: Petrol/Diesel | E7: City Fuel Station | F7: 1215 | G7: 0.18 | H7: =F7*G7 | I7: =F7+H7 | J7: Cash | K7: Received
A8: 45678 | B8: EXP-2025-107 | C8: Office Expenses | D8: Misc Purchase | E8: City Fuel Station | F8: 3771 | G8: 0.18 | H8: =F8*G8 | I8: =F8+H8 | J8: UPI | K8: Received
A9: 45671 | B9: EXP-2025-108 | C9: Marketing | D9: Google Ads | E9: Google Ads | F9: 9191 | G9: 0.18 | H9: =F9*G9 | I9: =F9+H9 | J9: Card | K9: Received
A10: 45665 | B10: EXP-2025-109 | C10: Office Expenses | D10: Misc Purchase | E10: Kumar Chemicals | F10: 538 | G10: 0.18 | H10: =F10*G10 | I10: =F10+H10 | J10: Cash | K10: Received
A11: 45660 | B11: EXP-2025-110 | C11: Vendor Payment | D11: Utility Bill | E11: Facebook Ads | F11: 1439 | G11: 0.18 | H11: =F11*G11 | I11: =F11+H11 | J11: Card | K11: Received
A12: 45670 | B12: EXP-2025-111 | C12: Marketing | D12: Google Ads | E12: Google Ads | F12: 14980 | G12: 0.18 | H12: =F12*G12 | I12: =F12+H12 | J12: Card | K12: Received
A13: 45660 | B13: EXP-2025-112 | C13: Vendor Payment | D13: Utility Bill | E13: Office Depot | F13: 2946 | G13: 0.18 | H13: =F13*G13 | I13: =F13+H13 | J13: Card | K13: Received
... A16: 45675 | B16: EXP-2025-115 | C16: Office Expenses | D16: Misc Purchase | E16: City Fuel Station | F16: 2434 | G16: 0.18 | H16: =F16*G16 | I16: =F16+H16 | J16: UPI | K16: Received

Sheet Employee Salaries
A1: Month | B1: Employee ID | C1: Employee Name | D1: Designation | E1: Department | F1: Basic Salary (₹) | G1: HRA (₹) | H1: Other Allowances (₹) | I1: Gross Salary (₹) | J1: PF Deduction (₹) | K1: ESI Deduction (₹) | L1: Other Deductions (₹) | M1: Total Deductions (₹) | N1: Net Salary (₹) | O1: Payment Date | P1: Payment Mode | Q1: Payment Status | R1: Notes
A2: January 2025 | B2: EMP001 | C2: Ramesh Kumar | D2: Driver | E2: Operations | F2: 18000 | G2: 0 | H2: 0 | I2: =F2+G2+H2 | J2: 0 | K2: 0 | L2: 0 | M2: =J2+K2+L2 | N2: =I2-M2 | O2: 45688 | P2: Bank Transfer | Q2: Paid
A3: January 2025 | B3: EMP002 | C3: Suresh Nair | D3: Technician | E3: Operations | F3: 22000 | G3: 0 | H3: 0 | I3: =F3+G3+H3 | J3: 0 | K3: 0 | L3: 0 | M3: =J3+K3+L3 | N3: =I3-M3 | O3: 45688 | P3: Bank Transfer | Q3: Paid
A4: January 2025 | B4: EMP003 | C4: Anil Sharma | D4: Helper | E4: Operations | F4: 15000 | G4: 0 | H4: 0 | I4: =F4+G4+H4 | J4: 0 | K4: 0 | L4: 0 | M4: =J4+K4+L4 | N4: =I4-M4 | O4: 45688 | P4: Bank Transfer | Q4: Paid
A5: January 2025 | B5: EMP004 | C5: Priya Menon | D5: Supervisor | E5: Operations | F5: 28000 | G5: 0 | H5: 0 | I5: =F5+G5+H5 | J5: 0 | K5: 0 | L5: 0 | M5: =J5+K5+L5 | N5: =I5-M5 | O5: 45688 | P5: Bank Transfer | Q5: Paid
A6: January 2025 | B6: EMP005 | C6: Karthik Reddy | D6: Technician | E6: Operations | F6: 22000 | G6: 0 | H6: 0 | I6: =F6+G6+H6 | J6: 0 | K6: 0 | L6: 0 | M6: =J6+K6+L6 | N6: =I6-M6 | O6: 45688 | P6: Bank Transfer | Q6: Paid
A7: January 2025 | B7: EMP006 | C7: Lakshmi Iyer | D7: Admin | E7: Office | F7: 20000 | G7: 0 | H7: 0 | I7: =F7+G7+H7 | J7: 0 | K7: 0 | L7: 0 | M7: =J7+K7+L7 | N7: =I7-M7 | O7: 45688 | P7: Bank Transfer | Q7: Paid
A8: January 2025 | B8: EMP007 | C8: Vijay Das | D8: Helper | E8: Operations | F8: 15000 | G8: 0 | H8: 0 | I8: =F8+G8+H8 | J8: 0 | K8: 0 | L8: 0 | M8: =J8+K8+L8 | N8: =I8-M8 | O8: 45688 | P8: Bank Transfer | Q8: Paid
A9: January 2025 | B9: EMP008 | C9: Meena Pillai | D9: Accounts | E9: Office | F9: 25000 | G9: 0 | H9: 0 | I9: =F9+G9+H9 | J9: 0 | K9: 0 | L9: 0 | M9: =J9+K9+L9 | N9: =I9-M9 | O9: 45688 | P9: Bank Transfer | Q9: Paid

Sheet Contractor Payments
A1: Date | B1: Payment ID | C1: Contractor Name | D1: Contractor PAN | E1: Service Type | F1: Project/Work Description | G1: Gross Amount (₹) | H1: TDS % (Sec 194C) | I1: TDS Amount (₹) | J1: Net Payable (₹) | K1: Payment Date | L1: Payment Mode | M1: Payment Status | N1: TDS Deposited | O1: Notes
A2: 45673 | B2: CONT-2025-301 | C2: Sharma Cleaning Services | D2: ABCPS1234A | E2: Deep Cleaning | F2: Green Valley Phase 1 | G2: 45000 | H2: 0.02 | I2: =G2*H2 | J2: =G2-I2 | K2: 45669 | L2: Bank Transfer | M2: Paid | N2: Yes
A3: 45668 | B3: CONT-2025-302 | C3: Krishna Pest Control | D3: DEFPK5678B | E3: Pest Control | F3: Tech Park Building A | G3: 35000 | H3: 0.02 | I3: =G3*H3 | J3: =G3-I3 | K3: 45672 | L3: Bank Transfer | M3: Pending | N3: No
A4: 45674 | B4: CONT-2025-303 | C4: Apex Painting Works | D4: GHIPA9012C | E4: Painting | F4: Residential Complex | G4: 85000 | H4: 0.02 | I4: =G4*H4 | J4: =G4-I4 | K4: 45681 | L4: UPI | M4: Paid | N4: Yes
A5: 45658 | B5: CONT-2025-304 | C5: City Plumbers | D5: JKLPC3456D | E5: Plumbing | F5: Apartment Maintenance | G5: 28000 | H5: 0.01 | I5: =G5*H5 | J5: =G5-I5 | K5: 45672 | L5: UPI | M5: Pending | N5: Yes
A6: 45682 | B6: CONT-2025-305 | C6: Royal AC Services | D6: MNOPR7890E | E6: AC Service | F6: Office Complex | G6: 42000 | H6: 0.02 | I6: =G6*H6 | J6: =G6-I6 | K6: 45667 | L6: Bank Transfer | M6: Paid | N6: Yes
A7: 45677 | B7: CONT-2025-306 | C7: Metro Electrical | D7: PQRME1234F | E7: Electrical | F7: New Installation | G7: 55000 | H7: 0.02 | I7: =G7*H7 | J7: =G7-I7 | K7: 45680 | L7: Cheque | M7: Pending | N7: No
A8: 45659 | B8: CONT-2025-307 | C8: Clean Pro Services | D8: STUCL5678G | E8: Regular Cleaning | F8: Monthly Contract | G8: 65000 | H8: 0.02 | I8: =G8*H8 | J8: =G8-I8 | K8: 45677 | L8: Bank Transfer | M8: Paid | N8: Yes
A9: 45659 | B9: CONT-2025-308 | C9: Pest Masters | D9: VWXPM9012H | E9: Pest Control | F9: Quarterly Treatment | G9: 48000 | H9: 0.02 | I9: =G9*H9 | J9: =G9-I9 | K9: 45682 | L9: Bank Transfer | M9: Paid | N9: No

Sheet Stock Purchases
A1: Date | B1: Purchase ID | C1: Vendor Name | D1: Vendor GSTIN | E1: Invoice No | F1: Item Type | G1: Item Name | H1: Quantity | I1: Unit | J1: Rate (₹) | K1: Base Amount (₹) | L1: GST % | M1: GST Amount (₹) | N1: Total Amount (₹) | O1: Payment Status | P1: Notes
A2: 45661 | B2: PO-2025-201 | C2: Metro Cleaning Supplies | D2: 29AABCM9012C3ZX | E2: INV/4453 | F2: Chemical | G2: Floor Cleaner | H2: 44 | I2: Liters | J2: 120 | K2: =H2*J2 | L2: 0.18 | M2: =K2*L2 | N2: =K2+M2 | O2: Pending
A3: 45682 | B3: PO-2025-202 | C3: Kumar Chemicals Pvt Ltd | D3: 29AABCK1234A1ZV | E3: INV/2623 | F3: Chemical | G3: Surface Disinfectant | H3: 46 | I3: Liters | J3: 180 | K3: =H3*J3 | L3: 0.18 | M3: =K3*L3 | N3: =K3+M3 | O3: Paid
A4: 45666 | B4: PO-2025-203 | C4: City Supplies | D4: 29AABCS5678B2ZW | E4: INV/5389 | F4: Accessory | G4: Microfiber Cloth | H4: 92 | I4: Pieces | J4: 80 | K4: =H4*J4 | L4: 0.18 | M4: =K4*L4 | N4: =K4+M4 | O4: Pending
A5: 45663 | B5: PO-2025-204 | C5: Metro Cleaning Supplies | D5: 29AABCM9012C3ZX | E5: INV/7216 | F5: Accessory | G5: Rubber Gloves | H5: 93 | I5: Pairs | J5: 45 | K5: =H5*J5 | L5: 0.18 | M5: =K5*L5 | N5: =K5+M5 | O5: Paid
A6: 45666 | B6: PO-2025-205 | C6: City Supplies | D6: 29AABCS5678B2ZW | E6: INV/3200 | F6: Chemical | G6: Floor Cleaner | H6: 23 | I6: Liters | J6: 120 | K6: =H6*J6 | L6: 0.18 | M6: =K6*L6 | N6: =K6+M6 | O6: Paid
A7: 45685 | B7: PO-2025-206 | C7: Metro Cleaning Supplies | D7: 29AABCM9012C3ZX | E7: INV/7037 | F7: Accessory | G7: Microfiber Cloth | H7: 46 | I7: Pieces | J7: 80 | K7: =H7*J7 | L7: 0.18 | M7: =K7*L7 | N7: =K7+M7 | O7: Pending
A8: 45681 | B8: PO-2025-207 | C8: Metro Cleaning Supplies | D8: 29AABCM9012C3ZX | E8: INV/4368 | F8: Accessory | G8: Microfiber Cloth | H8: 11 | I8: Pieces | J8: 80 | K8: =H8*J8 | L8: 0.18 | M8: =K8*L8 | N8: =K8+M8 | O8: Pending
A9: 45676 | B9: PO-2025-208 | C9: Kumar Chemicals Pvt Ltd | D9: 29AABCK1234A1ZV | E9: INV/7055 | F9: Accessory | G9: Microfiber Cloth | H9: 86 | I9: Pieces | J9: 80 | K9: =H9*J9 | L9: 0.18 | M9: =K9*L9 | N9: =K9+M9 | O9: Pending
A10: 45680 | B10: PO-2025-209 | C10: City Supplies | D10: 29AABCS5678B2ZW | E10: INV/1628 | F10: Chemical | G10: Glass Cleaner | H10: 57 | I10: Liters | J10: 95 | K10: =H10*J10 | L10: 0.18 | M10: =K10*L10 | N10: =K10+M10 | O10: Pending
A11: 45663 | B11: PO-2025-210 | C11: City Supplies | D11: 29AABCS5678B2ZW | E11: INV/6895 | F11: Chemical | G11: Floor Cleaner | H11: 37 | I11: Liters | J11: 120 | K11: =H11*J11 | L11: 0.18 | M11: =K11*L11 | N11: =K11+M11 | O11: Paid

Sheet Machines & Equipment
A1: Machine ID | B1: Machine Name | C1: Model | D1: Category | E1: Purchase Date | F1: Purchase Invoice No | G1: Vendor GST No | H1: Base Cost (₹) | I1: GST % | J1: GST Amount (₹) | K1: Total Cost (₹) | L1: Current Status | M1: Location | N1: Notes
A2: M001 | B2: Floor Scrubber | C2: Karcher BD 50/50 | D2: Cleaning Machine | E2: 45000 | F2: INV/K/2023/1234 | G2: 29AABCK1234A1Z5 | H2: 72034 | I2: 0.18 | J2: =H2*I2 | K2: =H2+J2 | L2: Active | M2: Team A
A3: M002 | B3: Pressure Washer | C3: Bosch AQT 45-14X | D3: Cleaning Machine | E3: 45066 | F3: INV/B/2023/5678 | G3: 29AABCB5678B2Z6 | H3: 38136 | I3: 0.18 | J3: =H3*I3 | K3: =H3+J3 | L3: Active | M3: Team B
A4: M003 | B4: Vacuum Cleaner | C4: Eureka Forbes Pro | D4: Cleaning Machine | E4: 44783 | F4: INV/E/2022/9012 | G4: 29AABCE9012C3Z7 | H4: 23729 | I4: 0.18 | J4: =H4*I4 | K4: =H4+J4 | L4: Active | M4: Team A
A5: M004 | B5: Pest Control Sprayer | C5: Solo 475 | D5: Spray Equipment | E5: 44931 | F5: INV/S/2023/3456 | G5: 29AABCS3456D4Z8 | H5: 12712 | I5: 0.18 | J5: =H5*I5 | K5: =H5+J5 | L5: Active | M5: Pest Team
A6: M005 | B6: Paint Sprayer | C6: Graco Magnum X5 | D6: Spray Equipment | E6: 45119 | F6: INV/G/2023/7890 | G6: 29AABCG7890E5Z9 | H6: 55085 | I6: 0.18 | J6: =H6*I6 | K6: =H6+J6 | L6: Under Repair | M6: Painting
A7: M006 | B7: Drill Machine | C7: Bosch GSB 600 | D7: Power Tools | E7: 44669 | F7: INV/B/2022/1111 | G7: 29AABCB5678B2Z6 | H7: 7203 | I7: 0.18 | J7: =H7*I7 | K7: =H7+J7 | L7: Active | M7: General
A8: M007 | B8: Angle Grinder | C8: Makita GA4030 | D8: Power Tools | E8: 44979 | F8: INV/M/2023/2222 | G8: 29AABCM2222F6Z0 | H8: 5508 | I8: 0.18 | J8: =H8*I8 | K8: =H8+J8 | L8: Active | M8: General
A9: M008 | B9: Steam Cleaner | C9: Karcher SC3 | D9: Cleaning Machine | E9: 45299 | F9: INV/K/2024/3333 | G9: 29AABCK1234A1Z5 | H9: 29661 | I9: 0.18 | J9: =H9*I9 | K9: =H9+J9 | L9: Active | M9: Team C

Sheet Machine Maintenance
A1: Date | B1: Machine ID | C1: Machine Name | D1: Maintenance Type | E1: Description | F1: Base Cost (₹) | G1: GST % | H1: GST Amount (₹) | I1: Total Cost (₹) | J1: Done By | K1: Next Service | L1: Service Status | M1: Notes
A2: 45505 | B2: M001 | C2: Floor Scrubber | D2: Service | E2: Brush replacement | F2: 3814 | G2: 0.18 | H2: =F2*G2 | I2: =F2+H2 | J2: Karcher Service | K2: 45689 | L2: Service Completed
A3: 45540 | B3: M002 | C3: Pressure Washer | D3: Repair | E3: Nozzle fixed | F3: 1525 | G3: 0.18 | H3: =F3*G3 | I3: =F3+H3 | J3: Bosch Service | K3: 45721 | L3: Service Completed
A4: 45575 | B4: M003 | C4: Vacuum Cleaner | D4: Service | E4: Filter cleaning | F4: 678 | G4: 0.18 | H4: =F4*G4 | I4: =F4+H4 | J4: In-house | K4: 45757 | L4: Service Completed
A5: 45611 | B5: M005 | C5: Paint Sprayer | D5: Repair | E5: Motor rewinding | F5: 7203 | G5: 0.18 | H5: =F5*G5 | I5: =F5+H5 | J5: Graco Service | K5: 45792 | L5: Out for Service
A6: 45662 | B6: M004 | C6: Pest Sprayer | D6: Service | E6: Valve check | F6: 424 | G6: 0.18 | H6: =F6*G6 | I6: =F6+H6 | J6: In-house | K6: 45843 | L6: Service Completed

Sheet Chemicals Stock
A1: Item ID | B1: Chemical Name | C1: Brand | D1: Category | E1: Unit | F1: Unit Rate (₹) | G1: Opening Stock | H1: Stock Added | I1: Stock Used | J1: Closing Stock | K1: Min Level | L1: Status | M1: Est. Value (₹) | N1: Last Updated
A2: CH001 | B2: Floor Cleaner | C2: Lizol | D2: Cleaning Agents | E2: Liters | F2: 120 | G2: 50 | H2: 100 | I2: 80 | J2: =G2+H2-I2 | K2: 20 | L2: =IF(J2<=K2,"Low Stock","OK") | M2: =J2*F2 | N2: 45682
A3: CH002 | B3: Glass Cleaner | C3: Colin | D3: Cleaning Agents | E3: Liters | F3: 95 | G3: 30 | H3: 50 | I3: 45 | J3: =G3+H3-I3 | K3: 15 | L3: =IF(J3<=K3,"Low Stock","OK") | M3: =J3*F3 | N3: 45682
A4: CH003 | B4: Toilet Cleaner | C4: Harpic | D4: Cleaning Agents | E4: Liters | F4: 110 | G4: 40 | H4: 80 | I4: 70 | J4: =G4+H4-I4 | K4: 20 | L4: =IF(J4<=K4,"Low Stock","OK") | M4: =J4*F4 | N4: 45682
A5: CH004 | B5: Pesticide Spray | C5: Baygon Pro | D5: Pest Control | E5: Cans | F5: 350 | G5: 25 | H5: 50 | I5: 40 | J5: =G5+H5-I5 | K5: 10 | L5: =IF(J5<=K5,"Low Stock","OK") | M5: =J5*F5 | N5: 45682
A6: CH005 | B6: Surface Disinfectant | C6: Lysol | D6: Sanitizers | E6: Liters | F6: 180 | G6: 25 | H6: 50 | I6: 40 | J6: =G6+H6-I6 | K6: 15 | L6: =IF(J6<=K6,"Low Stock","OK") | M6: =J6*F6 | N6: 45682

Sheet Accessories Stock
A1: Item ID | B1: Item Name | C1: Category | D1: Unit | E1: Unit Rate (₹) | F1: Opening Stock | G1: Stock Added | H1: Stock Used | I1: Closing Stock | J1: Min Level | K1: Status | L1: Est. Value (₹) | M1: Last Updated
A2: AC001 | B2: Rubber Hose (10m) | C2: Pipes & Hoses | D2: Pieces | E2: 450 | F2: 10 | G2: 15 | H2: 12 | I2: =F2+G2-H2 | J2: 5 | K2: =IF(I2<=J2,"Low Stock","OK") | L2: =I2*E2 | M2: 45682
A3: AC002 | B3: Floor Mop | C3: Brushes & Mops | D3: Pieces | E3: 250 | F3: 20 | G3: 30 | H3: 25 | I3: =F3+G3-H3 | J3: 10 | K3: =IF(I3<=J3,"Low Stock","OK") | L3: =I3*E3 | M3: 45682
A4: AC003 | B4: Microfiber Cloth | C4: Cloths & Wipes | D4: Pieces | E4: 80 | F4: 50 | G4: 100 | H4: 80 | I4: =F4+G4-H4 | J4: 25 | K4: =IF(I4<=J4,"Low Stock","OK") | L4: =I4*E4 | M4: 45682
A5: AC004 | B5: Rubber Gloves | C5: Gloves & Safety | D5: Pairs | E5: 45 | F5: 30 | G5: 50 | H5: 40 | I5: =F5+G5-H5 | J5: 15 | K5: =IF(I5<=J5,"Low Stock","OK") | L5: =I5*E5 | M5: 45682
A6: AC005 | B6: Spray Bottles | C6: Other | D6: Pieces | E6: 120 | F6: 20 | G6: 30 | H6: 22 | I6: =F6+G6-H6 | J6: 10 | K6: =IF(I6<=J6,"Low Stock","OK") | L6: =I6*E6 | M6: 45682

Sheet Stock Transactions
A1: Date | B1: Transaction ID | C1: Item Type | D1: Item ID | E1: Item Name | F1: Transaction Type | G1: Quantity | H1: Unit Rate (₹) | I1: Base Amount (₹) | J1: GST % | K1: GST Amount (₹) | L1: Total Cost (₹) | M1: Project/Team | N1: Notes
A2: 45659 | B2: TXN001 | C2: Chemical | D2: CH001 | E2: Floor Cleaner | F2: Purchase | G2: 50 | H2: 120 | I2: =G2*H2 | J2: 0.18 | K2: =I2*J2 | L2: =I2+K2 | M2: Warehouse
A3: 45662 | B3: TXN002 | C3: Accessory | D3: AC003 | E3: Microfiber Cloth | F3: Purchase | G3: 50 | H3: 80 | I3: =G3*H3 | J3: 0.18 | K3: =I3*J3 | L3: =I3+K3 | M3: Warehouse
A4: 45663 | B4: TXN003 | C4: Chemical | D4: CH001 | E4: Floor Cleaner | F4: Used | G4: 20 | H4: 0 | I4: =G4*H4 | J4: 0 | K4: =I4*J4 | L4: =I4+K4 | M4: Team A
A5: 45665 | B5: TXN004 | C5: Accessory | D5: AC004 | E5: Rubber Gloves | F5: Used | G5: 10 | H5: 0 | I5: =G5*H5 | J5: 0 | K5: =I5*J5 | L5: =I5+K5 | M5: Team B
A6: 45667 | B6: TXN005 | C6: Chemical | D6: CH002 | E6: Glass Cleaner | F6: Purchase | G6: 25 | H6: 95 | I6: =G6*H6 | J6: 0.18 | K6: =I6*J6 | L6: =I6+K6 | M6: Warehouse

Sheet GST Invoices
A1: Invoice Date | B1: Invoice Number | C1: Customer Name | D1: Service Type | E1: Base Amount (₹) | F1: GST % | G1: GST Amount (₹) | H1: Total Amount (₹) | I1: GST Payment Status | J1: Payment Date | K1: Notes
A2: 45668 | B2: GST-INV-2025-1001 | C2: Rahul Verma | D2: Painting | E2: 13199 | F2: 0.18 | G2: =E2*F2 | H2: =E2+G2 | I2: Pending
A3: 45671 | B3: GST-INV-2025-1002 | C3: Arun Krishnan | D3: Deep Cleaning | E3: 22126 | F3: 0.18 | G3: =E3*F3 | H3: =E3+G3 | I3: Paid | J3: 45680
A4: 45682 | B4: GST-INV-2025-1003 | C4: Manoj Das | D4: Pest Control | E4: 45225 | F4: 0.18 | G4: =E4*F4 | H4: =E4+G4 | I4: Pending
A5: 45671 | B5: GST-INV-2025-1004 | C5: Lakshmi Pillai | D5: Plumbing | E5: 48741 | F5: 0.18 | G5: =E5*F5 | H5: =E5+G5 | I5: Pending
A6: 45667 | B6: GST-INV-2025-1005 | C6: Sunita Reddy | D6: Pest Control | E6: 32265 | F6: 0.18 | G6: =E6*F6 | H6: =E6+G6 | I6: Paid | J6: 45681
A7: 45677 | B7: GST-INV-2025-1006 | C7: Rajesh Kumar | D7: AC Service | E7: 15002 | F7: 0.18 | G7: =E7*F7 | H7: =E7+G7 | I7: Paid | J7: 45684
A8: 45673 | B8: GST-INV-2025-1007 | C8: Arun Krishnan | D8: Plumbing | E8: 26315 | F8: 0.18 | G8: =E8*F8 | H8: =E8+G8 | I8: Paid | J8: 45680
A9: 45672 | B9: GST-INV-2025-1008 | C9: Anjali Menon | D9: Plumbing | E9: 16454 | F9: 0.18 | G9: =E9*F9 | H9: =E9+G9 | I9: Paid | J9: 45678
A10: 45663 | B10: GST-INV-2025-1009 | C10: Kavitha Srinivasan | D10: Pest Control | E10: 22824 | F10: 0.18 | G10: =E10*F10 | H10: =E10+G10 | I10: Paid | J10: 45674
A11: 45674 | B11: GST-INV-2025-1010 | C11: Kavitha Srinivasan | D11: Painting | E11: 32668 | F11: 0.18 | G11: =E11*F11 | H11: =E11+G11 | I11: Paid | J11: 45684

Sheet Income Summary
A1: INCOME SUMMARY REPORT
A3: SERVICE-WISE REVENUE
A4: Service Type | B4: Base Revenue (₹) | C4: Discount (₹) | D4: GST Collected (₹) | E4: Total Revenue (₹) | F4: Orders
A5: Deep Cleaning | B5: =SUMIF('Income Tracker'!D:D,A5,'Income Tracker'!G:G) | C5: =SUMIF('Income Tracker'!D:D,A5,'Income Tracker'!I:I) | D5: =SUMIF('Income Tracker'!D:D,A5,'Income Tracker'!L:L) | E5: =SUMIF('Income Tracker'!D:D,A5,'Income Tracker'!M:M) | F5: =COUNTIF('Income Tracker'!D:D,A5)
A6: Regular Cleaning | B6: =SUMIF('Income Tracker'!D:D,A6,'Income Tracker'!G:G) | C6: =SUMIF('Income Tracker'!D:D,A6,'Income Tracker'!I:I) | D6: =SUMIF('Income Tracker'!D:D,A6,'Income Tracker'!L:L) | E6: =SUMIF('Income Tracker'!D:D,A6,'Income Tracker'!M:M) | F6: =COUNTIF('Income Tracker'!D:D,A6)
A7: Pest Control | B7: =SUMIF('Income Tracker'!D:D,A7,'Income Tracker'!G:G) | C7: =SUMIF('Income Tracker'!D:D,A7,'Income Tracker'!I:I) | D7: =SUMIF('Income Tracker'!D:D,A7,'Income Tracker'!L:L) | E7: =SUMIF('Income Tracker'!D:D,A7,'Income Tracker'!M:M) | F7: =COUNTIF('Income Tracker'!D:D,A7)
A8: Painting | B8: =SUMIF('Income Tracker'!D:D,A8,'Income Tracker'!G:G) | C8: =SUMIF('Income Tracker'!D:D,A8,'Income Tracker'!I:I) | D8: =SUMIF('Income Tracker'!D:D,A8,'Income Tracker'!L:L) | E8: =SUMIF('Income Tracker'!D:D,A8,'Income Tracker'!M:M) | F8: =COUNTIF('Income Tracker'!D:D,A8)
A9: Plumbing | B9: =SUMIF('Income Tracker'!D:D,A9,'Income Tracker'!G:G) | C9: =SUMIF('Income Tracker'!D:D,A9,'Income Tracker'!I:I) | D9: =SUMIF('Income Tracker'!D:D,A9,'Income Tracker'!L:L) | E9: =SUMIF('Income Tracker'!D:D,A9,'Income Tracker'!M:M) | F9: =COUNTIF('Income Tracker'!D:D,A9)
A10: Electrical | B10: =SUMIF('Income Tracker'!D:D,A10,'Income Tracker'!G:G) | C10: =SUMIF('Income Tracker'!D:D,A10,'Income Tracker'!I:I) | D10: =SUMIF('Income Tracker'!D:D,A10,'Income Tracker'!L:L) | E10: =SUMIF('Income Tracker'!D:D,A10,'Income Tracker'!M:M) | F10: =COUNTIF('Income Tracker'!D:D,A10)
A11: Carpentry | B11: =SUMIF('Income Tracker'!D:D,A11,'Income Tracker'!G:G) | C11: =SUMIF('Income Tracker'!D:D,A11,'Income Tracker'!I:I) | D11: =SUMIF('Income Tracker'!D:D,A11,'Income Tracker'!L:L) | E11: =SUMIF('Income Tracker'!D:D,A11,'Income Tracker'!M:M) | F11: =COUNTIF('Income Tracker'!D:D,A11)
A12: AC Service | B12: =SUMIF('Income Tracker'!D:D,A12,'Income Tracker'!G:G) | C12: =SUMIF('Income Tracker'!D:D,A12,'Income Tracker'!I:I) | D12: =SUMIF('Income Tracker'!D:D,A12,'Income Tracker'!L:L) | E12: =SUMIF('Income Tracker'!D:D,A12,'Income Tracker'!M:M) | F12: =COUNTIF('Income Tracker'!D:D,A12)
A13: TOTAL | B13: =SUM(B5:B12) | C13: =SUM(C5:C12) | D13: =SUM(D5:D12) | E13: =SUM(E5:E12) | F13: =SUM(F5:F12)

Sheet Expense Summary
A1: EXPENSE SUMMARY REPORT
A3: CATEGORY-WISE EXPENSES
A4: Category | B4: Base Amount (₹) | C4: GST Paid (₹) | D4: Total Amount (₹) | E4: Count
A5: Vendor Payment | B5: =SUMIF('Expense Tracker'!C:C,A5,'Expense Tracker'!F:F) | C5: =SUMIF('Expense Tracker'!C:C,A5,'Expense Tracker'!H:H) | D5: =SUMIF('Expense Tracker'!C:C,A5,'Expense Tracker'!I:I) | E5: =COUNTIF('Expense Tracker'!C:C,A5)
A6: Travel & Fuel | B6: =SUMIF('Expense Tracker'!C:C,A6,'Expense Tracker'!F:F) | C6: =SUMIF('Expense Tracker'!C:C,A6,'Expense Tracker'!H:H) | D6: =SUMIF('Expense Tracker'!C:C,A6,'Expense Tracker'!I:I) | E6: =COUNTIF('Expense Tracker'!C:C,A6)
A7: Marketing | B7: =SUMIF('Expense Tracker'!C:C,A7,'Expense Tracker'!F:F) | C7: =SUMIF('Expense Tracker'!C:C,A7,'Expense Tracker'!H:H) | D7: =SUMIF('Expense Tracker'!C:C,A7,'Expense Tracker'!I:I) | E7: =COUNTIF('Expense Tracker'!C:C,A7)
A8: Office Expenses | B8: =SUMIF('Expense Tracker'!C:C,A8,'Expense Tracker'!F:F) | C8: =SUMIF('Expense Tracker'!C:C,A8,'Expense Tracker'!H:H) | D8: =SUMIF('Expense Tracker'!C:C,A8,'Expense Tracker'!I:I) | E8: =COUNTIF('Expense Tracker'!C:C,A8)
A9: Miscellaneous | B9: =SUMIF('Expense Tracker'!C:C,A9,'Expense Tracker'!F:F) | C9: =SUMIF('Expense Tracker'!C:C,A9,'Expense Tracker'!H:H) | D9: =SUMIF('Expense Tracker'!C:C,A9,'Expense Tracker'!I:I) | E9: =COUNTIF('Expense Tracker'!C:C,A9)
A10: TOTAL | B10: =SUM(B5:B9) | C10: =SUM(C5:C9) | D10: =SUM(D5:D9) | E10: =SUM(E5:E9)

Sheet GST Summary
A1: GST SUMMARY REPORT
A3: GST COLLECTED (OUTPUT TAX)
A4: Source | B4: Base Amount (₹) | C4: GST Amount (₹)
A5: Service Revenue | B5: =SUM('Income Tracker'!J:J) | C5: =SUM('Income Tracker'!L:L)
A6: TOTAL GST COLLECTED | B6: =B5 | C6: =C5
A9: GST PAID (INPUT TAX)
A10: Source | B10: Base Amount (₹) | C10: GST Amount (₹)
A11: Expenses | B11: =SUM('Expense Tracker'!F:F) | C11: =SUM('Expense Tracker'!H:H)
A12: Stock Purchases | B12: =SUM('Stock Purchases'!K:K) | C12: =SUM('Stock Purchases'!M:M)
A13: Machine Purchases | B13: =SUM('Machines & Equipment'!H:H) | C13: =SUM('Machines & Equipment'!J:J)
A14: Maintenance | B14: =SUM('Machine Maintenance'!F:F) | C14: =SUM('Machine Maintenance'!H:H)
A15: TOTAL GST PAID | B15: =SUM(B11:B14) | C15: =SUM(C11:C14)
A18: GST INVOICE STATUS
A19: GST Paid (from Invoices) | B19: =SUMIF('GST Invoices'!I:I,"Paid",'GST Invoices'!G:G)
A20: GST Pending (from Invoices) | B20: =SUMIF('GST Invoices'!I:I,"Pending",'GST Invoices'!G:G)
A23: NET GST PAYABLE | C23: =C6-C15

Sheet TDS Summary
A1: TDS SUMMARY REPORT
A2: (For TDS Filing - Section 194C)
A4: TDS DEDUCTED FROM CONTRACTORS
A5: Metric | B5: Amount (₹)
A6: Total Contractor Payments (Gross) | B6: =SUM('Contractor Payments'!G:G)
A7: Total TDS Deducted | B7: =SUM('Contractor Payments'!I:I)
A8: Total Net Paid to Contractors | B8: =SUM('Contractor Payments'!J:J)
A9: TDS Deposited | B9: =SUMIF('Contractor Payments'!N:N,"Yes",'Contractor Payments'!I:I)
A10: TDS Pending Deposit | B10: =B7-B9

Sheet Stock Reports
A1: DETAILED STOCK REPORTS
A3: CHEMICALS STOCK SUMMARY
A4: Item ID | B4: Chemical Name | C4: Unit Rate (₹) | D4: Current Stock | E4: Min Level | F4: Status | G4: Est. Value (₹)
A5: ='Chemicals Stock'!A2 | B5: ='Chemicals Stock'!B2 | C5: ='Chemicals Stock'!F2 | D5: ='Chemicals Stock'!J2 | E5: ='Chemicals Stock'!K2 | F5: ='Chemicals Stock'!L2 | G5: ='Chemicals Stock'!M2
A6: ='Chemicals Stock'!A3 | B6: ='Chemicals Stock'!B3 | C6: ='Chemicals Stock'!F3 | D6: ='Chemicals Stock'!J3 | E6: ='Chemicals Stock'!K3 | F6: ='Chemicals Stock'!L3 | G6: ='Chemicals Stock'!M3
A7: ='Chemicals Stock'!A4 | B7: ='Chemicals Stock'!B4 | C7: ='Chemicals Stock'!F4 | D7: ='Chemicals Stock'!J4 | E7: ='Chemicals Stock'!K4 | F7: ='Chemicals Stock'!L4 | G7: ='Chemicals Stock'!M4
A8: ='Chemicals Stock'!A5 | B8: ='Chemicals Stock'!B5 | C8: ='Chemicals Stock'!F5 | D8: ='Chemicals Stock'!J5 | E8: ='Chemicals Stock'!K5 | F8: ='Chemicals Stock'!L5 | G8: ='Chemicals Stock'!M5
A9: ='Chemicals Stock'!A6 | B9: ='Chemicals Stock'!B6 | C9: ='Chemicals Stock'!F6 | D9: ='Chemicals Stock'!J6 | E9: ='Chemicals Stock'!K6 | F9: ='Chemicals Stock'!L6 | G9: ='Chemicals Stock'!M6
A10: TOTAL | D10: =SUM(D5:D9) | G10: =SUM(G5:G9)
A13: ACCESSORIES STOCK SUMMARY
A14: Item ID | B14: Item Name | C14: Unit Rate (₹) | D14: Current Stock | E14: Min Level | F14: Status | G14: Est. Value (₹)
A15: ='Accessories Stock'!A2 | B15: ='Accessories Stock'!B2 | C15: ='Accessories Stock'!E2 | D15: ='Accessories Stock'!I2 | E15: ='Accessories Stock'!J2 | F15: ='Accessories Stock'!K2 | G15: ='Accessories Stock'!L2
A16: ='Accessories Stock'!A3 | B16: ='Accessories Stock'!B3 | C16: ='Accessories Stock'!E3 | D16: ='Accessories Stock'!I3 | E16: ='Accessories Stock'!J3 | F16: ='Accessories Stock'!K3 | G16: ='Accessories Stock'!L3
A17: ='Accessories Stock'!A4 | B17: ='Accessories Stock'!B4 | C17: ='Accessories Stock'!E4 | D17: ='Accessories Stock'!I4 | E17: ='Accessories Stock'!J4 | F17: ='Accessories Stock'!K4 | G17: ='Accessories Stock'!L4
A18: ='Accessories Stock'!A5 | B18: ='Accessories Stock'!B5 | C18: ='Accessories Stock'!E5 | D18: ='Accessories Stock'!I5 | E18: ='Accessories Stock'!J5 | F18: ='Accessories Stock'!K5 | G18: ='Accessories Stock'!L5
A19: ='Accessories Stock'!A6 | B19: ='Accessories Stock'!B6 | C19: ='Accessories Stock'!E6 | D19: ='Accessories Stock'!I6 | E19: ='Accessories Stock'!J6 | F19: ='Accessories Stock'!K6 | G19: ='Accessories Stock'!L6
A20: TOTAL | D20: =SUM(D15:D19) | G20: =SUM(G15:G19)
A23: MACHINE ASSET SUMMARY
A24: Category | B24: Count | C24: Base Value (₹) | D24: GST (₹) | E24: Total Value (₹)
A25: Cleaning Machine | B25: =COUNTIF('Machines & Equipment'!D:D,A25) | C25: =SUMIF('Machines & Equipment'!D:D,A25,'Machines & Equipment'!H:H) | D25: =SUMIF('Machines & Equipment'!D:D,A25,'Machines & Equipment'!J:J) | E25: =SUMIF('Machines & Equipment'!D:D,A25,'Machines & Equipment'!K:K)
A26: Spray Equipment | B26: =COUNTIF('Machines & Equipment'!D:D,A26) | C26: =SUMIF('Machines & Equipment'!D:D,A26,'Machines & Equipment'!H:H) | D26: =SUMIF('Machines & Equipment'!D:D,A26,'Machines & Equipment'!J:J) | E26: =SUMIF('Machines & Equipment'!D:D,A26,'Machines & Equipment'!K:K)
A27: Power Tools | B27: =COUNTIF('Machines & Equipment'!D:D,A27) | C27: =SUMIF('Machines & Equipment'!D:D,A27,'Machines & Equipment'!H:H) | D27: =SUMIF('Machines & Equipment'!D:D,A27,'Machines & Equipment'!J:J) | E27: =SUMIF('Machines & Equipment'!D:D,A27,'Machines & Equipment'!K:K)
A28: Safety Equipment | B28: =COUNTIF('Machines & Equipment'!D:D,A28) | C28: =SUMIF('Machines & Equipment'!D:D,A28,'Machines & Equipment'!H:H) | D28: =SUMIF('Machines & Equipment'!D:D,A28,'Machines & Equipment'!J:J) | E28: =SUMIF('Machines & Equipment'!D:D,A28,'Machines & Equipment'!K:K)
A29: TOTAL | B29: =SUM(B25:B28) | C29: =SUM(C25:C28) | D29: =SUM(D25:D28) | E29: =SUM(E25:E28)
A32: STOCK PURCHASE SUMMARY
A33: Total Stock Purchases (Base) | B33: =SUM('Stock Purchases'!K:K)
A34: Total GST on Purchases | B34: =SUM('Stock Purchases'!M:M)
A35: Total with GST | B35: =SUM('Stock Purchases'!N:N)
A36: Paid | B36: =SUMIF('Stock Purchases'!O:O,"Paid",'Stock Purchases'!N:N)
A37: Pending | B37: =SUMIF('Stock Purchases'!O:O,"Pending",'Stock Purchases'!N:N)

Sheet Profitability Report
A1: PROFITABILITY ANALYSIS
A3: ACTUAL NET PROFIT CALCULATION
A4: Description | B4: Amount (₹)
A5: TOTAL REVENUE (After Discount, excl. GST) | B5: =SUM('Income Tracker'!J:J)
A7: Less: Operating Expenses | B7: =SUM('Expense Tracker'!F:F)
A8: Less: Employee Salaries | B8: =SUM('Employee Salaries'!N:N)
A9: Less: Contractor Payments | B9: =SUM('Contractor Payments'!J:J)
A10: Less: Stock Purchases | B10: =SUM('Stock Purchases'!K:K)
A11: Less: Machine Maintenance | B11: =SUM('Machine Maintenance'!F:F)
A13: TOTAL EXPENSES | B13: =B6+B7+B8+B9+B10
A15: NET PROFIT / (LOSS) | B15: =B5-B12
A17: Net Profit Margin % | B17: =IF(B5>0,B14/B5,0)

Sheet Dashboard
A1: MIS DASHBOARD
A3: DATE FILTER SETTINGS
A4: Enter dates below to filter Dashboard reports:
A5: From Date: | B5: 45658 | C5: To Date: | D5: 45688
A6: Change the dates above to filter all metrics below
A8: KEY FINANCIAL METRICS (FILTERED BY DATE)
A9: TOTAL REVENUE | C9: TOTAL EXPENSES | E9: CONTRACTOR PAY | G9: GST COLLECTED | I9: STOCK PURCHASES
A10: =SUMIFS('Income Tracker'!M:M,'Income Tracker'!A:A,">="&B5,'Income Tracker'!A:A,"<="&D5) | C10: =SUMIFS('Expense Tracker'!I:I,'Expense Tracker'!A:A,">="&B5,'Expense Tracker'!A:A,"<="&D5) | E10: =SUMIFS('Contractor Payments'!J:J,'Contractor Payments'!A:A,">="&B5,'Contractor Payments'!A:A,"<="&D5) | G10: =SUMIFS('Income Tracker'!L:L,'Income Tracker'!A:A,">="&B5,'Income Tracker'!A:A,"<="&D5) | I10: =SUMIFS('Stock Purchases'!N:N,'Stock Purchases'!A:A,">="&B5,'Stock Purchases'!A:A,"<="&D5)
A12: NET PROFIT | C12: TOTAL ORDERS | E12: GST PAID | G12: NET GST PAYABLE | I12: TDS DEDUCTED
A13: =SUMIFS('Income Tracker'!J:J,'Income Tracker'!A:A,">="&B5,'Income Tracker'!A:A,"<="&D5)-SUMIFS('Expense Tracker'!F:F,'Expense Tracker'!A:A,">="&B5,'Expense Tracker'!A:A,"<="&D5)-SUMIFS('Contractor Payments'!J:J,'Contractor Payments'!A:A,">="&B5,'Contractor Payments'!A:A,"<="&D5)-SUMIFS('Stock Purchases'!K:K,'Stock Purchases'!A:A,">="&B5,'Stock Purchases'!A:A,"<="&D5) | C13: =COUNTIFS('Income Tracker'!A:A,">="&B5,'Income Tracker'!A:A,"<="&D5) | E13: =SUMIFS('Expense Tracker'!H:H,'Expense Tracker'!A:A,">="&B5,'Expense Tracker'!A:A,"<="&D5)+SUMIFS('Stock Purchases'!M:M,'Stock Purchases'!A:A,">="&B5,'Stock Purchases'!A:A,"<="&D5) | G13: =G10-E13 | I13: =SUMIFS('Contractor Payments'!I:I,'Contractor Payments'!A:A,">="&B5,'Contractor Payments'!A:A,"<="&D5)
A15: ALL TIME SUMMARY (WITHOUT DATE FILTER)
A16: Total Revenue (All) | B16: =SUM('Income Tracker'!M:M) | C16: Total Expenses (All) | D16: =SUM('Expense Tracker'!I:I)+SUM('Employee Salaries'!N:N)+SUM('Contractor Payments'!J:J)+SUM('Stock Purchases'!N:N)+SUM('Machine Maintenance'!I:I) | E16: Total Profit (All) | F16: =SUM('Income Tracker'!J:J)-SUM('Expense Tracker'!F:F)-SUM('Employee Salaries'!N:N)-SUM('Contractor Payments'!J:J)-SUM('Stock Purchases'!K:K)-SUM('Machine Maintenance'!F:F) | G16: Total Orders | H16: =COUNTA('Income Tracker'!A:A)-1 | I16: Total Employees | J16: =COUNTA('Employee Salaries'!B:B)-1
A18: PENDING ITEMS (ACTION REQUIRED)
A19: Pending Income | B19: =SUMIF('Income Tracker'!O:O,"Pending",'Income Tracker'!M:M) | C19: Pending Expenses | D19: =SUMIF('Expense Tracker'!K:K,"Pending",'Expense Tracker'!I:I) | E19: GST Pending | F19: =SUMIF('GST Invoices'!I:I,"Pending",'GST Invoices'!G:G) | G19: TDS Pending Deposit | H19: =SUM('Contractor Payments'!I:I)-SUMIF('Contractor Payments'!N:N,"Yes",'Contractor Payments'!I:I) | I19: Stock Payment Pending | J19: =SUMIF('Stock Purchases'!O:O,"Pending",'Stock Purchases'!N:N)
