Workbook

Sheet HOW TO USE
A3: SHEET | B3: PURPOSE | C3: HOW TO USE
A4: Income Tracker | B4: Record all service revenue | C4: Enter each payment received with service type and project details
A5: Expense Tracker | B5: Track all business expenses | C5: Log every expense with category and payment details
A6: Machines & Equipment | B6: Asset register for all machines | C6: Add each machine with unique ID (M001, M002...)
A7: Machine Maintenance | B7: Track repairs and servicing | C7: Log every repair/service against machine ID
A8: Chemicals Stock | B8: Manage chemical inventory | C8: Update stock added and used regularly
A9: Accessories Stock | B9: Track consumables inventory | C9: Update purchases and usage daily
A10: Stock Transactions | B10: Detailed stock movement log | C10: Record every purchase/usage transaction
A11: Income Summary | B11: Auto-calculated revenue reports | C11: View only - auto-updates from Income Tracker
A12: Expense Summary | B12: Auto-calculated expense reports | C12: View only - auto-updates from Expense Tracker
A13: Profitability Report | B13: Profit analysis | C13: View only - auto-calculates profit margins
A14: Stock Reports | B14: Inventory status and alerts | C14: View only - shows low stock and asset values
A15: Dashboard | B15: Visual overview with charts | C15: View only - key metrics at a glance
A17: TIPS:
A18: 1. Use dropdowns for consistency
A19: 2. Enter data daily for accurate reports
A20: 3. Check Dashboard weekly for insights
A21: 4. Monitor Low Stock alerts regularly

Sheet Income Tracker
A1: Date | B1: Invoice No | C1: Customer Name | D1: Service Type | E1: Project Type | F1: Project Name | G1: Amount (₹) | H1: Payment Mode | I1: Payment Status | J1: Notes
A2: 45677 | B2: INV-2025-1001 | C2: Rajesh Kumar | D2: AC Service | E2: Apartment Bulk | F2: Green Valley Apartments | G2: 136765 | H2: Cash | I2: Received
A3: 45680 | B3: INV-2025-1002 | C3: Priya Sharma | D3: Deep Cleaning | E3: Individual | G3: 10841 | H3: Cash | I3: Received
A4: 45675 | B4: INV-2025-1003 | C4: Amit Patel | D4: Regular Cleaning | E4: Commercial | F4: Tech Park | G4: 129748 | H4: Cash | I4: Pending
A5: 45684 | B5: INV-2025-1004 | C5: Sunita Reddy | D5: Pest Control | E5: Commercial | F5: Tech Park | G5: 53183 | H5: Cash | I5: Pending
A6: 45680 | B6: INV-2025-1005 | C6: Vikram Singh | D6: Carpentry | E6: Individual | G6: 23046 | H6: Cash | I6: Pending
A7: 45674 | B7: INV-2025-1006 | C7: Deepa Nair | D7: Regular Cleaning | E7: Individual | G7: 3713 | H7: Card | I7: Received
A8: 45677 | B8: INV-2025-1007 | C8: Karthik Iyer | D8: Carpentry | E8: Commercial | F8: Tech Park | G8: 199740 | H8: Bank Transfer | I8: Pending
A9: 45675 | B9: INV-2025-1008 | C9: Meena Gupta | D9: Deep Cleaning | E9: Apartment Bulk | F9: Green Valley Apartments | G9: 79680 | H9: UPI | I9: Pending
A10: 45675 | B10: INV-2025-1009 | C10: Rahul Verma | D10: Regular Cleaning | E10: Individual | G10: 5952 | H10: Bank Transfer | I10: Pending
A11: 45664 | B11: INV-2025-1010 | C11: Anjali Menon | D11: Painting | E11: Commercial | F11: Tech Park | G11: 114172 | H11: Card | I11: Pending
A12: 45676 | B12: INV-2025-1011 | C12: Suresh Rao | D12: Painting | E12: Individual | G12: 7290 | H12: Cash | I12: Received
A13: 45678 | B13: INV-2025-1012 | C13: Lakshmi Pillai | D13: Painting | E13: Individual | G13: 13452 | H13: Cash | I13: Pending
A14: 45681 | B14: INV-2025-1013 | C14: Arun Krishnan | D14: Regular Cleaning | E14: Individual | G14: 16149 | H14: Card | I14: Received
A15: 45674 | B15: INV-2025-1014 | C15: Kavitha Srinivasan | D15: Painting | E15: Commercial | F15: Tech Park | G15: 51666 | H15: Card | I15: Pending
A16: 45682 | B16: INV-2025-1015 | C16: Manoj Das | D16: Electrical | E16: Individual | G16: 12583 | H16: Cash | I16: Received

Sheet Expense Tracker
A1: Date | B1: Expense ID | C1: Category | D1: Description | E1: Vendor/Payee | F1: Amount (₹) | G1: Payment Mode | H1: Payment Status | I1: Notes
A2: 45659 | B2: EXP-2025-101 | C2: Office Expenses | D2: Misc Purchase | E2: Security Agency | F2: 3532 | G2: UPI | H2: Pending
A3: 45681 | B3: EXP-2025-102 | C3: Vendor Payment | D3: Office Supplies | E3: Suresh (Technician) | F3: 3497 | G3: Bank Transfer | H3: Pending
A4: 45660 | B4: EXP-2025-103 | C4: Office Expenses | D4: Misc Purchase | E4: Facebook Ads | F4: 2425 | G4: UPI | H4: Received
A5: 45685 | B5: EXP-2025-104 | C5: Vendor Payment | D5: Office Supplies | E5: City Fuel Station | F5: 3956 | G5: Cash | H5: Pending
A6: 45672 | B6: EXP-2025-105 | C6: Miscellaneous | D6: Misc Purchase | E6: Electricity Board | F6: 2452 | G6: Bank Transfer | H6: Pending
A7: 45676 | B7: EXP-2025-106 | C7: Staff Salary | D7: Salary - Driver | E7: Kumar | F7: 25522 | G7: UPI | H7: Pending
A8: 45679 | B8: EXP-2025-107 | C8: Marketing | D8: Facebook Ads | E8: Facebook Ads | F8: 8956 | G8: UPI | H8: Received
A9: 45674 | B9: EXP-2025-108 | C9: Office Expenses | D9: Misc Purchase | E9: Office Depot | F9: 962 | G9: Card | H9: Pending
A10: 45680 | B10: EXP-2025-109 | C10: Office Expenses | D10: Office Supplies | E10: City Fuel Station | F10: 3115 | G10: Card | H10: Pending
A11: 45670 | B11: EXP-2025-110 | C11: Travel & Fuel | D11: Petrol/Diesel | E11: City Fuel Station | F11: 2987 | G11: Bank Transfer | H11: Pending
A12: 45663 | B12: EXP-2025-111 | C12: Marketing | D12: Google Ads | E12: Google Ads | F12: 2220 | G12: Card | H12: Received
A13: 45665 | B13: EXP-2025-112 | C13: Travel & Fuel | D13: Petrol/Diesel | E13: City Fuel Station | F13: 1785 | G13: UPI | H13: Received
... A21: 45683 | B21: EXP-2025-120 | C21: Marketing | D21: Facebook Ads | E21: Facebook Ads | F21: 14998 | G21: Card | H21: Received

Sheet Machines & Equipment
A1: Machine ID | B1: Machine Name | C1: Model | D1: Category | E1: Purchase Date | F1: Purchase Cost (₹) | G1: Current Status | H1: Location/Assigned To | I1: Notes
A2: M001 | B2: Floor Scrubber | C2: Karcher BD 50/50 | D2: Cleaning Machine | E2: 45000 | F2: 85000 | G2: Active | H2: Team A
A3: M002 | B3: Pressure Washer | C3: Bosch AQT 45-14X | D3: Cleaning Machine | E3: 45066 | F3: 45000 | G3: Active | H3: Team B
A4: M003 | B4: Vacuum Cleaner | C4: Eureka Forbes Pro | D4: Cleaning Machine | E4: 44783 | F4: 28000 | G4: Active | H4: Team A
A5: M004 | B5: Pest Control Sprayer | C5: Solo 475 | D5: Spray Equipment | E5: 44931 | F5: 15000 | G5: Active | H5: Pest Team
A6: M005 | B6: Paint Sprayer | C6: Graco Magnum X5 | D6: Spray Equipment | E6: 45119 | F6: 65000 | G6: Under Repair | H6: Painting Team | I6: Motor issue
A7: M006 | B7: Drill Machine | C7: Bosch GSB 600 | D7: Power Tools | E7: 44669 | F7: 8500 | G7: Active | H7: General
A8: M007 | B8: Angle Grinder | C8: Makita GA4030 | D8: Power Tools | E8: 44979 | F8: 6500 | G8: Active | H8: General
A9: M008 | B9: Ladder (12ft) | C9: Aluminium | D9: Safety Equipment | E9: 44571 | F9: 12000 | G9: Active | H9: Warehouse
A10: M009 | B10: Steam Cleaner | C10: Karcher SC3 | D10: Cleaning Machine | E10: 45299 | F10: 35000 | G10: Active | H10: Team C
A11: M010 | B11: Industrial Blower | C11: Dewalt DCE100 | D11: Cleaning Machine | E11: 45235 | F11: 18000 | G11: Retired | H11: Storage | I11: Replaced

Sheet Machine Maintenance
A1: Date | B1: Machine ID | C1: Machine Name | D1: Maintenance Type | E1: Description | F1: Cost (₹) | G1: Done By | H1: Next Service Due | I1: Notes
A2: 45332 | B2: M001 | C2: Floor Scrubber | D2: Service | E2: Regular servicing | F2: 2500 | G2: Karcher Service | H2: 45514
A3: 45366 | B3: M002 | C3: Pressure Washer | D3: Parts Replacement | E3: Nozzle replaced | F3: 1200 | G3: Local Mechanic | H3: 45550
A4: 45387 | B4: M003 | C4: Vacuum Cleaner | D4: Service | E4: Filter cleaning | F4: 800 | G4: In-house | H4: 45570
A5: 45432 | B5: M005 | C5: Paint Sprayer | D5: Repair | E5: Motor rewinding | F5: 8500 | G5: Graco Service | H5: 45616 | I5: Under warranty
A6: 45451 | B6: M004 | C6: Pest Control Sprayer | D6: Service | E6: Valve check | F6: 500 | G6: In-house | H6: 45634
A7: 45485 | B7: M006 | C7: Drill Machine | D7: Parts Replacement | E7: Chuck replaced | F7: 1500 | G7: Bosch Service | H7: 45669
A8: 45505 | B8: M001 | C8: Floor Scrubber | D8: Service | E8: Brush replacement | F8: 4500 | G8: Karcher Service | H8: 45689
A9: 45522 | B9: M007 | C9: Angle Grinder | D9: Repair | E9: Switch repair | F9: 600 | G9: Local Mechanic | H9: 45706
A10: 45540 | B10: M009 | C10: Steam Cleaner | D10: Service | E10: Descaling | F10: 1200 | G10: Karcher Service | H10: 45721
A11: 45575 | B11: M002 | C11: Pressure Washer | D11: Service | E11: Regular maintenance | F11: 1800 | G11: Bosch Service | H11: 45757
A12: 45611 | B12: M003 | C12: Vacuum Cleaner | D12: Parts Replacement | E12: Motor replaced | F12: 5500 | G12: Eureka Service | H12: 45792
A13: 45627 | B13: M005 | C13: Paint Sprayer | D13: Repair | E13: Hose replacement | F13: 2200 | G13: Graco Service | H13: 45809 | I13: Still under repair
A14: 45662 | B14: M004 | C14: Pest Control Sprayer | D14: Service | E14: Annual service | F14: 1000 | G14: Solo Service | H14: 45843
A15: 45672 | B15: M006 | C15: Drill Machine | D15: Service | E15: Oiling & cleaning | F15: 300 | G15: In-house | H15: 45853
A16: 45677 | B16: M009 | C16: Steam Cleaner | D16: Parts Replacement | E16: Gasket replaced | F16: 800 | G16: Karcher Service | H16: 45858

Sheet Chemicals Stock
A1: Item ID | B1: Chemical Name | C1: Brand | D1: Category | E1: Unit | F1: Opening Stock | G1: Stock Added | H1: Stock Used | I1: Closing Stock | J1: Min Level | K1: Status | L1: Last Updated
A2: CH001 | B2: Floor Cleaner | C2: Lizol | D2: Cleaning Agents | E2: Liters | F2: 50 | G2: 100 | H2: 80 | I2: =F2+G2-H2 | J2: 20 | K2: =IF(I2<J2,"Low Stock","OK") | L2: 45682
A3: CH002 | B3: Glass Cleaner | C3: Colin | D3: Cleaning Agents | E3: Liters | F3: 30 | G3: 50 | H3: 45 | I3: =F3+G3-H3 | J3: 15 | K3: =IF(I3<J3,"Low Stock","OK") | L3: 45682
A4: CH003 | B4: Toilet Cleaner | C4: Harpic | D4: Cleaning Agents | E4: Liters | F4: 40 | G4: 80 | H4: 70 | I4: =F4+G4-H4 | J4: 20 | K4: =IF(I4<J4,"Low Stock","OK") | L4: 45682
A5: CH004 | B5: Pesticide Spray | C5: Baygon Pro | D5: Pest Control | E5: Cans | F5: 25 | G5: 50 | H5: 55 | I5: =F5+G5-H5 | J5: 10 | K5: =IF(I5<J5,"Low Stock","OK") | L5: 45682
A6: CH005 | B6: Termite Solution | C6: Premise | D6: Pest Control | E6: Liters | F6: 20 | G6: 40 | H6: 35 | I6: =F6+G6-H6 | J6: 10 | K6: =IF(I6<J6,"Low Stock","OK") | L6: 45682
A7: CH006 | B7: Hand Sanitizer | C7: Dettol | D7: Sanitizers | E7: Liters | F7: 15 | G7: 30 | H7: 28 | I7: =F7+G7-H7 | J7: 10 | K7: =IF(I7<J7,"Low Stock","OK") | L7: 45682
A8: CH007 | B8: Surface Disinfectant | C8: Lysol | D8: Sanitizers | E8: Liters | F8: 25 | G8: 50 | H8: 40 | I8: =F8+G8-H8 | J8: 15 | K8: =IF(I8<J8,"Low Stock","OK") | L8: 45682
A9: CH008 | B9: Degreaser | C9: WD-40 | D9: Specialty | E9: Cans | F9: 10 | G9: 20 | H9: 18 | I9: =F9+G9-H9 | J9: 5 | K9: =IF(I9<J9,"Low Stock","OK") | L9: 45682
A10: CH009 | B10: Stain Remover | C10: Vanish | D10: Specialty | E10: KG | F10: 8 | G10: 15 | H10: 12 | I10: =F10+G10-H10 | J10: 5 | K10: =IF(I10<J10,"Low Stock","OK") | L10: 45682
A11: CH010 | B11: Air Freshener | C11: Odonil | D11: Specialty | E11: Cans | F11: 30 | G11: 60 | H11: 65 | I11: =F11+G11-H11 | J11: 15 | K11: =IF(I11<J11,"Low Stock","OK") | L11: 45682
A12: CH011 | B12: Cockroach Gel | C12: Advion | D12: Pest Control | E12: Bottles | F12: 20 | G12: 30 | H12: 25 | I12: =F12+G12-H12 | J12: 10 | K12: =IF(I12<J12,"Low Stock","OK") | L12: 45682
A13: CH012 | B13: Fabric Softener | C13: Comfort | D13: Cleaning Agents | E13: Liters | F13: 15 | G13: 25 | H13: 22 | I13: =F13+G13-H13 | J13: 10 | K13: =IF(I13<J13,"Low Stock","OK") | L13: 45682

Sheet Accessories Stock
A1: Item ID | B1: Item Name | C1: Category | D1: Unit | E1: Opening Stock | F1: Stock Added | G1: Stock Used | H1: Closing Stock | I1: Min Level | J1: Status | K1: Last Updated
A2: AC001 | B2: Rubber Hose (10m) | C2: Pipes & Hoses | D2: Pieces | E2: 10 | F2: 15 | G2: 12 | H2: =E2+F2-G2 | I2: 5 | J2: =IF(H2<I2,"Low Stock","OK") | K2: 45682
A3: AC002 | B3: Floor Mop | C3: Brushes & Mops | D3: Pieces | E3: 20 | F3: 30 | G3: 28 | H3: =E3+F3-G3 | I3: 10 | J3: =IF(H3<I3,"Low Stock","OK") | K3: 45682
A4: AC003 | B4: Scrub Brush | C4: Brushes & Mops | D4: Pieces | E4: 25 | F4: 40 | G4: 35 | H4: =E4+F4-G4 | I4: 10 | J4: =IF(H4<I4,"Low Stock","OK") | K4: 45682
A5: AC004 | B5: Microfiber Cloth | C5: Cloths & Wipes | D5: Pieces | E5: 50 | F5: 100 | G5: 90 | H5: =E5+F5-G5 | I5: 25 | J5: =IF(H5<I5,"Low Stock","OK") | K5: 45682
A6: AC005 | B6: Rubber Gloves | C6: Gloves & Safety | D6: Pairs | E6: 30 | F6: 50 | G6: 48 | H6: =E6+F6-G6 | I6: 15 | J6: =IF(H6<I6,"Low Stock","OK") | K6: 45682
A7: AC006 | B7: Safety Goggles | C7: Gloves & Safety | D7: Pieces | E7: 10 | F7: 15 | G7: 8 | H7: =E7+F7-G7 | I7: 5 | J7: =IF(H7<I7,"Low Stock","OK") | K7: 45682
A8: AC007 | B8: Spray Bottles | C8: Other | D8: Pieces | E8: 20 | F8: 30 | G8: 22 | H8: =E8+F8-G8 | I8: 10 | J8: =IF(H8<I8,"Low Stock","OK") | K8: 45682
A9: AC008 | B9: Dust Pan Set | C9: Brushes & Mops | D9: Sets | E9: 15 | F9: 20 | G9: 18 | H9: =E9+F9-G9 | I9: 8 | J9: =IF(H9<I9,"Low Stock","OK") | K9: 45682
A10: AC009 | B10: Extension Cord | C10: Tools | D10: Pieces | E10: 8 | F10: 10 | G10: 7 | H10: =E10+F10-G10 | I10: 4 | J10: =IF(H10<I10,"Low Stock","OK") | K10: 45682
A11: AC010 | B11: Bucket (20L) | C11: Other | D11: Pieces | E11: 25 | F11: 30 | G11: 28 | H11: =E11+F11-G11 | I11: 10 | J11: =IF(H11<I11,"Low Stock","OK") | K11: 45682
A12: AC011 | B12: Face Masks | C12: Gloves & Safety | D12: Boxes | E12: 10 | F12: 20 | G12: 18 | H12: =E12+F12-G12 | I12: 5 | J12: =IF(H12<I12,"Low Stock","OK") | K12: 45682
A13: AC012 | B13: Sponge Pack | C13: Cloths & Wipes | D13: Packs | E13: 20 | F13: 35 | G13: 30 | H13: =E13+F13-G13 | I13: 10 | J13: =IF(H13<I13,"Low Stock","OK") | K13: 45682
... A16: AC015 | B16: Tarpaulin Sheet | C16: Other | D16: Pieces | E16: 8 | F16: 12 | G16: 10 | H16: =E16+F16-G16 | I16: 4 | J16: =IF(H16<I16,"Low Stock","OK") | K16: 45682

Sheet Stock Transactions
A1: Date | B1: Transaction ID | C1: Item Type | D1: Item ID | E1: Item Name | F1: Transaction Type | G1: Quantity | H1: Unit Cost (₹) | I1: Total Cost (₹) | J1: Project/Team | K1: Notes
A2: 45659 | B2: TXN001 | C2: Chemical | D2: CH001 | E2: Floor Cleaner | F2: Purchase | G2: 50 | H2: 120 | I2: =G2*H2 | J2: Warehouse | K2: Monthly stock
A3: 45660 | B3: TXN002 | C3: Chemical | D3: CH004 | E3: Pesticide Spray | F3: Purchase | G3: 25 | H3: 350 | I3: =G3*H3 | J3: Warehouse
A4: 45662 | B4: TXN003 | C4: Accessory | D4: AC004 | E4: Microfiber Cloth | F4: Purchase | G4: 50 | H4: 80 | I4: =G4*H4 | J4: Warehouse | K4: Bulk order
A5: 45663 | B5: TXN004 | C5: Chemical | D5: CH001 | E5: Floor Cleaner | F5: Used | G5: 20 | H5: 0 | I5: =G5*H5 | J5: Team A | K5: Green Valley project
A6: 45664 | B6: TXN005 | C6: Accessory | D6: AC005 | E6: Rubber Gloves | F6: Used | G6: 10 | H6: 0 | I6: =G6*H6 | J6: Team B
A7: 45665 | B7: TXN006 | C7: Chemical | D7: CH002 | E7: Glass Cleaner | F7: Purchase | G7: 25 | H7: 95 | I7: =G7*H7 | J7: Warehouse
A8: 45667 | B8: TXN007 | C8: Accessory | D8: AC002 | E8: Floor Mop | F8: Damaged | G8: 2 | H8: 0 | I8: =G8*H8 | J8: Team A | K8: Worn out
A9: 45668 | B9: TXN008 | C9: Chemical | D9: CH007 | E9: Surface Disinfectant | F9: Used | G9: 15 | H9: 0 | I9: =G9*H9 | J9: Team C | K9: Hospital contract
A10: 45669 | B10: TXN009 | C10: Accessory | D10: AC003 | E10: Scrub Brush | F10: Purchase | G10: 20 | H10: 45 | I10: =G10*H10 | J10: Warehouse
A11: 45671 | B11: TXN010 | C11: Chemical | D11: CH005 | E11: Termite Solution | F11: Purchase | G11: 20 | H11: 850 | I11: =G11*H11 | J11: Warehouse
A12: 45672 | B12: TXN011 | C12: Accessory | D12: AC001 | E12: Rubber Hose (10m) | F12: Used | G12: 3 | H12: 0 | I12: =G12*H12 | J12: Pest Team
A13: 45673 | B13: TXN012 | C13: Chemical | D13: CH003 | E13: Toilet Cleaner | F13: Used | G13: 25 | H13: 0 | I13: =G13*H13 | J13: Team B
A14: 45675 | B14: TXN013 | C14: Accessory | D14: AC011 | E14: Face Masks | F14: Purchase | G14: 10 | H14: 250 | I14: =G14*H14 | J14: Warehouse
A15: 45676 | B15: TXN014 | C15: Chemical | D15: CH006 | E15: Hand Sanitizer | F15: Used | G15: 8 | H15: 0 | I15: =G15*H15 | J15: All Teams
A16: 45677 | B16: TXN015 | C16: Accessory | D16: AC007 | E16: Spray Bottles | F16: Returned | G16: 3 | H16: 0 | I16: =G16*H16 | J16: Team A | K16: Extra stock
A17: 45678 | B17: TXN016 | C17: Chemical | D17: CH010 | E17: Air Freshener | F17: Purchase | G17: 30 | H17: 180 | I17: =G17*H17 | J17: Warehouse
A18: 45679 | B18: TXN017 | C18: Accessory | D18: AC006 | E18: Safety Goggles | F18: Used | G18: 3 | H18: 0 | I18: =G18*H18 | J18: Painting Team
A19: 45680 | B19: TXN018 | C19: Chemical | D19: CH008 | E19: Degreaser | F19: Used | G19: 5 | H19: 0 | I19: =G19*H19 | J19: Team C | K19: Kitchen cleaning
A20: 45681 | B20: TXN019 | C20: Accessory | D20: AC012 | E20: Sponge Pack | F20: Purchase | G20: 15 | H20: 120 | I20: =G20*H20 | J20: Warehouse
A21: 45682 | B21: TXN020 | C21: Chemical | D21: CH011 | E21: Cockroach Gel | F21: Used | G21: 8 | H21: 0 | I21: =G21*H21 | J21: Pest Team

Sheet Income Summary
A1: INCOME SUMMARY REPORT
A3: SERVICE-WISE REVENUE
A4: Service Type | B4: Total Revenue (₹) | C4: Order Count | D4: Avg Order Value
A5: Deep Cleaning | B5: =SUMIF('Income Tracker'!D:D,A5,'Income Tracker'!G:G) | C5: =COUNTIF('Income Tracker'!D:D,A5) | D5: =IF(C5>0,B5/C5,0)
A6: Regular Cleaning | B6: =SUMIF('Income Tracker'!D:D,A6,'Income Tracker'!G:G) | C6: =COUNTIF('Income Tracker'!D:D,A6) | D6: =IF(C6>0,B6/C6,0)
A7: Pest Control | B7: =SUMIF('Income Tracker'!D:D,A7,'Income Tracker'!G:G) | C7: =COUNTIF('Income Tracker'!D:D,A7) | D7: =IF(C7>0,B7/C7,0)
A8: Painting | B8: =SUMIF('Income Tracker'!D:D,A8,'Income Tracker'!G:G) | C8: =COUNTIF('Income Tracker'!D:D,A8) | D8: =IF(C8>0,B8/C8,0)
A9: Plumbing | B9: =SUMIF('Income Tracker'!D:D,A9,'Income Tracker'!G:G) | C9: =COUNTIF('Income Tracker'!D:D,A9) | D9: =IF(C9>0,B9/C9,0)
A10: Electrical | B10: =SUMIF('Income Tracker'!D:D,A10,'Income Tracker'!G:G) | C10: =COUNTIF('Income Tracker'!D:D,A10) | D10: =IF(C10>0,B10/C10,0)
A11: Carpentry | B11: =SUMIF('Income Tracker'!D:D,A11,'Income Tracker'!G:G) | C11: =COUNTIF('Income Tracker'!D:D,A11) | D11: =IF(C11>0,B11/C11,0)
A12: AC Service | B12: =SUMIF('Income Tracker'!D:D,A12,'Income Tracker'!G:G) | C12: =COUNTIF('Income Tracker'!D:D,A12) | D12: =IF(C12>0,B12/C12,0)
A13: TOTAL | B13: =SUM(B5:B12) | C13: =SUM(C5:C12)
A16: PROJECT TYPE REVENUE
A17: Project Type | B17: Total Revenue (₹) | C17: Order Count
A18: Individual | B18: =SUMIF('Income Tracker'!E:E,A18,'Income Tracker'!G:G) | C18: =COUNTIF('Income Tracker'!E:E,A18)
A19: Apartment Bulk | B19: =SUMIF('Income Tracker'!E:E,A19,'Income Tracker'!G:G) | C19: =COUNTIF('Income Tracker'!E:E,A19)
A20: Commercial | B20: =SUMIF('Income Tracker'!E:E,A20,'Income Tracker'!G:G) | C20: =COUNTIF('Income Tracker'!E:E,A20)
A23: PAYMENT STATUS
A24: Status | B24: Amount (₹) | C24: Count
A25: Received | B25: =SUMIF('Income Tracker'!I:I,"Received",'Income Tracker'!G:G) | C25: =COUNTIF('Income Tracker'!I:I,"Received")
A26: Pending | B26: =SUMIF('Income Tracker'!I:I,"Pending",'Income Tracker'!G:G) | C26: =COUNTIF('Income Tracker'!I:I,"Pending")

Sheet Expense Summary
A1: EXPENSE SUMMARY REPORT
A3: CATEGORY-WISE EXPENSES
A4: Category | B4: Total Amount (₹) | C4: Transaction Count | D4: Avg Transaction
A5: Staff Salary | B5: =SUMIF('Expense Tracker'!C:C,A5,'Expense Tracker'!F:F) | C5: =COUNTIF('Expense Tracker'!C:C,A5) | D5: =IF(C5>0,B5/C5,0)
A6: Vendor Payment | B6: =SUMIF('Expense Tracker'!C:C,A6,'Expense Tracker'!F:F) | C6: =COUNTIF('Expense Tracker'!C:C,A6) | D6: =IF(C6>0,B6/C6,0)
A7: Travel & Fuel | B7: =SUMIF('Expense Tracker'!C:C,A7,'Expense Tracker'!F:F) | C7: =COUNTIF('Expense Tracker'!C:C,A7) | D7: =IF(C7>0,B7/C7,0)
A8: Marketing | B8: =SUMIF('Expense Tracker'!C:C,A8,'Expense Tracker'!F:F) | C8: =COUNTIF('Expense Tracker'!C:C,A8) | D8: =IF(C8>0,B8/C8,0)
A9: Office Expenses | B9: =SUMIF('Expense Tracker'!C:C,A9,'Expense Tracker'!F:F) | C9: =COUNTIF('Expense Tracker'!C:C,A9) | D9: =IF(C9>0,B9/C9,0)
A10: Miscellaneous | B10: =SUMIF('Expense Tracker'!C:C,A10,'Expense Tracker'!F:F) | C10: =COUNTIF('Expense Tracker'!C:C,A10) | D10: =IF(C10>0,B10/C10,0)
A11: TOTAL | B11: =SUM(B5:B10) | C11: =SUM(C5:C10)
A14: PAYMENT STATUS
A15: Status | B15: Amount (₹) | C15: Count
A16: Received | B16: =SUMIF('Expense Tracker'!H:H,"Received",'Expense Tracker'!F:F) | C16: =COUNTIF('Expense Tracker'!H:H,"Received")
A17: Pending | B17: =SUMIF('Expense Tracker'!H:H,"Pending",'Expense Tracker'!F:F) | C17: =COUNTIF('Expense Tracker'!H:H,"Pending")

Sheet Profitability Report
A1: PROFITABILITY ANALYSIS
A3: OVERALL PROFITABILITY
A4: Metric | B4: Amount (₹)
A5: Total Revenue | B5: =SUM('Income Tracker'!G:G)
A6: Total Expenses | B6: =SUM('Expense Tracker'!F:F)
A7: Gross Profit | B7: =B5-B6
A8: Profit Margin % | B8: =IF(B5>0,B7/B5,0)
A11: SERVICE-WISE PROFITABILITY
A12: Service | B12: Revenue (₹) | C12: % of Total
A13: Deep Cleaning | B13: =SUMIF('Income Tracker'!D:D,A13,'Income Tracker'!G:G) | C13: =IF($B$5>0,B13/$B$5,0)
A14: Regular Cleaning | B14: =SUMIF('Income Tracker'!D:D,A14,'Income Tracker'!G:G) | C14: =IF($B$5>0,B14/$B$5,0)
A15: Pest Control | B15: =SUMIF('Income Tracker'!D:D,A15,'Income Tracker'!G:G) | C15: =IF($B$5>0,B15/$B$5,0)
A16: Painting | B16: =SUMIF('Income Tracker'!D:D,A16,'Income Tracker'!G:G) | C16: =IF($B$5>0,B16/$B$5,0)
A17: Plumbing | B17: =SUMIF('Income Tracker'!D:D,A17,'Income Tracker'!G:G) | C17: =IF($B$5>0,B17/$B$5,0)
A18: Electrical | B18: =SUMIF('Income Tracker'!D:D,A18,'Income Tracker'!G:G) | C18: =IF($B$5>0,B18/$B$5,0)
A19: Carpentry | B19: =SUMIF('Income Tracker'!D:D,A19,'Income Tracker'!G:G) | C19: =IF($B$5>0,B19/$B$5,0)
A20: AC Service | B20: =SUMIF('Income Tracker'!D:D,A20,'Income Tracker'!G:G) | C20: =IF($B$5>0,B20/$B$5,0)

Sheet Stock Reports
A1: STOCK & INVENTORY REPORTS
A3: LOW STOCK ALERTS
A4: Item Type | B4: Item ID | C4: Item Name | D4: Current Stock | E4: Min Level
A5: Chemicals with Low Stock:
A6: (Check Chemicals Stock sheet - Status column shows 'Low Stock' items)
A8: Accessories with Low Stock:
A9: (Check Accessories Stock sheet - Status column shows 'Low Stock' items)
A12: ASSET VALUE SUMMARY
A13: Category | B13: Total Value (₹) | C13: Active Count | D13: Under Repair | E13: Retired
A14: Cleaning Machine | B14: =SUMIF('Machines & Equipment'!D:D,A14,'Machines & Equipment'!F:F) | C14: =COUNTIFS('Machines & Equipment'!D:D,A14,'Machines & Equipment'!G:G,"Active") | D14: =COUNTIFS('Machines & Equipment'!D:D,A14,'Machines & Equipment'!G:G,"Under Repair") | E14: =COUNTIFS('Machines & Equipment'!D:D,A14,'Machines & Equipment'!G:G,"Retired")
A15: Spray Equipment | B15: =SUMIF('Machines & Equipment'!D:D,A15,'Machines & Equipment'!F:F) | C15: =COUNTIFS('Machines & Equipment'!D:D,A15,'Machines & Equipment'!G:G,"Active") | D15: =COUNTIFS('Machines & Equipment'!D:D,A15,'Machines & Equipment'!G:G,"Under Repair") | E15: =COUNTIFS('Machines & Equipment'!D:D,A15,'Machines & Equipment'!G:G,"Retired")
A16: Power Tools | B16: =SUMIF('Machines & Equipment'!D:D,A16,'Machines & Equipment'!F:F) | C16: =COUNTIFS('Machines & Equipment'!D:D,A16,'Machines & Equipment'!G:G,"Active") | D16: =COUNTIFS('Machines & Equipment'!D:D,A16,'Machines & Equipment'!G:G,"Under Repair") | E16: =COUNTIFS('Machines & Equipment'!D:D,A16,'Machines & Equipment'!G:G,"Retired")
A17: Safety Equipment | B17: =SUMIF('Machines & Equipment'!D:D,A17,'Machines & Equipment'!F:F) | C17: =COUNTIFS('Machines & Equipment'!D:D,A17,'Machines & Equipment'!G:G,"Active") | D17: =COUNTIFS('Machines & Equipment'!D:D,A17,'Machines & Equipment'!G:G,"Under Repair") | E17: =COUNTIFS('Machines & Equipment'!D:D,A17,'Machines & Equipment'!G:G,"Retired")
A18: TOTAL ASSET VALUE | B18: =SUM('Machines & Equipment'!F:F) | C18: =COUNTIF('Machines & Equipment'!G:G,"Active") | D18: =COUNTIF('Machines & Equipment'!G:G,"Under Repair") | E18: =COUNTIF('Machines & Equipment'!G:G,"Retired")
A21: MAINTENANCE COST SUMMARY
A22: Maintenance Type | B22: Total Cost (₹) | C22: Count
A23: Repair | B23: =SUMIF('Machine Maintenance'!D:D,A23,'Machine Maintenance'!F:F) | C23: =COUNTIF('Machine Maintenance'!D:D,A23)
A24: Service | B24: =SUMIF('Machine Maintenance'!D:D,A24,'Machine Maintenance'!F:F) | C24: =COUNTIF('Machine Maintenance'!D:D,A24)
A25: Parts Replacement | B25: =SUMIF('Machine Maintenance'!D:D,A25,'Machine Maintenance'!F:F) | C25: =COUNTIF('Machine Maintenance'!D:D,A25)
A26: TOTAL MAINTENANCE | B26: =SUM('Machine Maintenance'!F:F)

Sheet Dashboard
A1: MIS DASHBOARD
A3: KEY METRICS
A4: Total Revenue | B4: =SUM('Income Tracker'!G:G) | C4: Total Expenses | D4: =SUM('Expense Tracker'!F:F)
A5: Net Profit | B5: =B4-D4 | C5: Profit Margin | D5: =IF(B4>0,B5/B4,0)
A6: Active Machines | B6: =COUNTIF('Machines & Equipment'!G:G,"Active") | C6: Machines Under Repair | D6: =COUNTIF('Machines & Equipment'!G:G,"Under Repair")
A7: Pending Payments | B7: =SUMIF('Income Tracker'!I:I,"Pending",'Income Tracker'!G:G) | C7: Pending Expenses | D7: =SUMIF('Expense Tracker'!H:H,"Pending",'Expense Tracker'!F:F)
A9: SERVICE PERFORMANCE | E9: EXPENSE BREAKDOWN
A10: Service | B10: Revenue | C10: Orders | E10: Category | F10: Amount | G10: Count
A11: Deep Cleaning | B11: =SUMIF('Income Tracker'!D:D,A11,'Income Tracker'!G:G) | C11: =COUNTIF('Income Tracker'!D:D,A11) | E11: Staff Salary | F11: =SUMIF('Expense Tracker'!C:C,E11,'Expense Tracker'!F:F) | G11: =COUNTIF('Expense Tracker'!C:C,E11)
A12: Regular Cleaning | B12: =SUMIF('Income Tracker'!D:D,A12,'Income Tracker'!G:G) | C12: =COUNTIF('Income Tracker'!D:D,A12) | E12: Vendor Payment | F12: =SUMIF('Expense Tracker'!C:C,E12,'Expense Tracker'!F:F) | G12: =COUNTIF('Expense Tracker'!C:C,E12)
A13: Pest Control | B13: =SUMIF('Income Tracker'!D:D,A13,'Income Tracker'!G:G) | C13: =COUNTIF('Income Tracker'!D:D,A13) | E13: Travel & Fuel | F13: =SUMIF('Expense Tracker'!C:C,E13,'Expense Tracker'!F:F) | G13: =COUNTIF('Expense Tracker'!C:C,E13)
A14: Painting | B14: =SUMIF('Income Tracker'!D:D,A14,'Income Tracker'!G:G) | C14: =COUNTIF('Income Tracker'!D:D,A14) | E14: Marketing | F14: =SUMIF('Expense Tracker'!C:C,E14,'Expense Tracker'!F:F) | G14: =COUNTIF('Expense Tracker'!C:C,E14)
A15: Plumbing | B15: =SUMIF('Income Tracker'!D:D,A15,'Income Tracker'!G:G) | C15: =COUNTIF('Income Tracker'!D:D,A15) | E15: Office Expenses | F15: =SUMIF('Expense Tracker'!C:C,E15,'Expense Tracker'!F:F) | G15: =COUNTIF('Expense Tracker'!C:C,E15)
A16: Electrical | B16: =SUMIF('Income Tracker'!D:D,A16,'Income Tracker'!G:G) | C16: =COUNTIF('Income Tracker'!D:D,A16) | E16: Miscellaneous | F16: =SUMIF('Expense Tracker'!C:C,E16,'Expense Tracker'!F:F) | G16: =COUNTIF('Expense Tracker'!C:C,E16)
A17: Carpentry | B17: =SUMIF('Income Tracker'!D:D,A17,'Income Tracker'!G:G) | C17: =COUNTIF('Income Tracker'!D:D,A17)
A18: AC Service | B18: =SUMIF('Income Tracker'!D:D,A18,'Income Tracker'!G:G) | C18: =COUNTIF('Income Tracker'!D:D,A18)
A21: STOCK STATUS
A22: Total Asset Value (Machines) | B22: =SUM('Machines & Equipment'!F:F)
A23: Total Maintenance Cost | B23: =SUM('Machine Maintenance'!F:F)
A24: Stock Transactions This Month | B24: =COUNTA('Stock Transactions'!A:A)-1
