Workbook

Sheet HOW TO USE
A3: SHEET | B3: PURPOSE | C3: HOW TO USE
A4: Income Tracker | B4: Record all service revenue with GST | C4: Enter each payment with service type, GST rate auto-calculates
A5: Expense Tracker | B5: Track all expenses with GST | C5: Log every expense with category and GST details
A6: Stock Purchases | B6: Track all stock/inventory purchases | C6: Record vendor purchases with invoice and GST
A7: Machines & Equipment | B7: Asset register for all machines | C7: Add each machine with unique ID (M001, M002...)
A8: Machine Maintenance | B8: Track repairs and servicing | C8: Log every repair/service against machine ID
A9: Chemicals Stock | B9: Manage chemical inventory | C9: Update stock added and used regularly
A10: Accessories Stock | B10: Track consumables inventory | C10: Update purchases and usage daily
A11: Stock Transactions | B11: Detailed stock movement log | C11: Record every purchase/usage transaction
A12: Income Summary | B12: Auto-calculated revenue reports | C12: View only - auto-updates from Income Tracker
A13: Expense Summary | B13: Auto-calculated expense reports | C13: View only - auto-updates from Expense Tracker
A14: GST Summary | B14: GST collected vs paid report | C14: View only - for GST filing reference
... A17: Dashboard | B17: Visual overview with charts | C17: View only - key metrics at a glance
A19: GST RATES:
A20: 5% - Basic services
A21: 12% - Standard services
A22: 18% - Most services (default)

Sheet Income Tracker
A1: Date | B1: Invoice No | C1: Customer Name | D1: Service Type | E1: Project Type | F1: Project Name | G1: Base Amount (₹) | H1: GST % | I1: GST Amount (₹) | J1: Total Amount (₹) | K1: Payment Mode | L1: Payment Status | M1: Notes
A2: 45663 | B2: INV-2025-1001 | C2: Rajesh Kumar | D2: Regular Cleaning | E2: Apartment Bulk | F2: Green Valley Apartments | G2: 161714 | H2: 0.18 | I2: =G2*H2 | J2: =G2+I2 | K2: UPI | L2: Received
A3: 45683 | B3: INV-2025-1002 | C3: Priya Sharma | D3: Electrical | E3: Individual | G3: 19560 | H3: 0.18 | I3: =G3*H3 | J3: =G3+I3 | K3: Cash | L3: Pending
A4: 45678 | B4: INV-2025-1003 | C4: Amit Patel | D4: Regular Cleaning | E4: Apartment Bulk | F4: Green Valley Apartments | G4: 71722 | H4: 0.18 | I4: =G4*H4 | J4: =G4+I4 | K4: Card | L4: Pending
A5: 45675 | B5: INV-2025-1004 | C5: Sunita Reddy | D5: Plumbing | E5: Individual | G5: 2406 | H5: 0.18 | I5: =G5*H5 | J5: =G5+I5 | K5: Card | L5: Pending
A6: 45664 | B6: INV-2025-1005 | C6: Vikram Singh | D6: Carpentry | E6: Commercial | F6: Tech Park | G6: 165480 | H6: 0.18 | I6: =G6*H6 | J6: =G6+I6 | K6: UPI | L6: Received
A7: 45658 | B7: INV-2025-1006 | C7: Deepa Nair | D7: AC Service | E7: Apartment Bulk | F7: Green Valley Apartments | G7: 70090 | H7: 0.18 | I7: =G7*H7 | J7: =G7+I7 | K7: UPI | L7: Pending
A8: 45663 | B8: INV-2025-1007 | C8: Karthik Iyer | D8: Painting | E8: Commercial | F8: Tech Park | G8: 65024 | H8: 0.18 | I8: =G8*H8 | J8: =G8+I8 | K8: Card | L8: Received
A9: 45681 | B9: INV-2025-1008 | C9: Meena Gupta | D9: Carpentry | E9: Apartment Bulk | F9: Green Valley Apartments | G9: 136501 | H9: 0.18 | I9: =G9*H9 | J9: =G9+I9 | K9: Cash | L9: Pending
A10: 45674 | B10: INV-2025-1009 | C10: Rahul Verma | D10: Deep Cleaning | E10: Individual | G10: 14814 | H10: 0.18 | I10: =G10*H10 | J10: =G10+I10 | K10: Card | L10: Received
A11: 45660 | B11: INV-2025-1010 | C11: Anjali Menon | D11: Painting | E11: Commercial | F11: Tech Park | G11: 54156 | H11: 0.18 | I11: =G11*H11 | J11: =G11+I11 | K11: Card | L11: Pending
A12: 45686 | B12: INV-2025-1011 | C12: Suresh Rao | D12: Painting | E12: Commercial | F12: Tech Park | G12: 123499 | H12: 0.18 | I12: =G12*H12 | J12: =G12+I12 | K12: UPI | L12: Received
A13: 45674 | B13: INV-2025-1012 | C13: Lakshmi Pillai | D13: Carpentry | E13: Individual | G13: 10596 | H13: 0.18 | I13: =G13*H13 | J13: =G13+I13 | K13: Bank Transfer | L13: Pending
A14: 45683 | B14: INV-2025-1013 | C14: Arun Krishnan | D14: Carpentry | E14: Apartment Bulk | F14: Green Valley Apartments | G14: 51159 | H14: 0.18 | I14: =G14*H14 | J14: =G14+I14 | K14: Card | L14: Received
A15: 45665 | B15: INV-2025-1014 | C15: Kavitha Srinivasan | D15: Deep Cleaning | E15: Commercial | F15: Tech Park | G15: 54942 | H15: 0.18 | I15: =G15*H15 | J15: =G15+I15 | K15: Bank Transfer | L15: Received
A16: 45669 | B16: INV-2025-1015 | C16: Manoj Das | D16: Pest Control | E16: Apartment Bulk | F16: Green Valley Apartments | G16: 110319 | H16: 0.18 | I16: =G16*H16 | J16: =G16+I16 | K16: UPI | L16: Pending

Sheet Expense Tracker
A1: Date | B1: Expense ID | C1: Category | D1: Description | E1: Vendor/Payee | F1: Base Amount (₹) | G1: GST % | H1: GST Amount (₹) | I1: Total Amount (₹) | J1: Payment Mode | K1: Payment Status | L1: Notes
A2: 45679 | B2: EXP-2025-101 | C2: Office Expenses | D2: Office Supplies | E2: Ramesh (Driver) | F2: 1650 | G2: 0.18 | H2: =F2*G2 | I2: =F2+H2 | J2: Cash | K2: Received
A3: 45678 | B3: EXP-2025-102 | C3: Miscellaneous | D3: Office Supplies | E3: Ramesh (Driver) | F3: 3268 | G3: 0.18 | H3: =F3*G3 | I3: =F3+H3 | J3: UPI | K3: Received
A4: 45678 | B4: EXP-2025-103 | C4: Vendor Payment | D4: Misc Purchase | E4: Kumar Chemicals | F4: 2827 | G4: 0.18 | H4: =F4*G4 | I4: =F4+H4 | J4: Cash | K4: Pending
A5: 45681 | B5: EXP-2025-104 | C5: Staff Salary | D5: Salary - Helper | E5: Suresh | F5: 24490 | G5: 0 | H5: =F5*G5 | I5: =F5+H5 | J5: Bank Transfer | K5: Pending
A6: 45682 | B6: EXP-2025-105 | C6: Miscellaneous | D6: Office Supplies | E6: Facebook Ads | F6: 690 | G6: 0.18 | H6: =F6*G6 | I6: =F6+H6 | J6: UPI | K6: Received
A7: 45679 | B7: EXP-2025-106 | C7: Office Expenses | D7: Utility Bill | E7: Facebook Ads | F7: 4405 | G7: 0.18 | H7: =F7*G7 | I7: =F7+H7 | J7: Bank Transfer | K7: Pending
A8: 45667 | B8: EXP-2025-107 | C8: Office Expenses | D8: Misc Purchase | E8: City Fuel Station | F8: 1694 | G8: 0.18 | H8: =F8*G8 | I8: =F8+H8 | J8: UPI | K8: Received
A9: 45658 | B9: EXP-2025-108 | C9: Miscellaneous | D9: Office Supplies | E9: Facebook Ads | F9: 3070 | G9: 0.18 | H9: =F9*G9 | I9: =F9+H9 | J9: Card | K9: Pending
A10: 45681 | B10: EXP-2025-109 | C10: Vendor Payment | D10: Utility Bill | E10: Airtel | F10: 1457 | G10: 0.18 | H10: =F10*G10 | I10: =F10+H10 | J10: Bank Transfer | K10: Pending
A11: 45671 | B11: EXP-2025-110 | C11: Travel & Fuel | D11: Petrol/Diesel | E11: City Fuel Station | F11: 1591 | G11: 0.18 | H11: =F11*G11 | I11: =F11+H11 | J11: Bank Transfer | K11: Pending
A12: 45680 | B12: EXP-2025-111 | C12: Miscellaneous | D12: Misc Purchase | E12: Office Depot | F12: 2030 | G12: 0.18 | H12: =F12*G12 | I12: =F12+H12 | J12: UPI | K12: Received
A13: 45659 | B13: EXP-2025-112 | C13: Staff Salary | D13: Salary - Driver | E13: Kumar | F13: 29232 | G13: 0 | H13: =F13*G13 | I13: =F13+H13 | J13: Card | K13: Received
... A21: 45660 | B21: EXP-2025-120 | C21: Office Expenses | D21: Utility Bill | E21: City Fuel Station | F21: 4673 | G21: 0.18 | H21: =F21*G21 | I21: =F21+H21 | J21: UPI | K21: Pending

Sheet Stock Purchases
A1: Date | B1: Purchase ID | C1: Vendor Name | D1: Vendor GSTIN | E1: Invoice No | F1: Item Type | G1: Item Name | H1: Quantity | I1: Unit | J1: Rate (₹) | K1: Base Amount (₹) | L1: GST % | M1: GST Amount (₹) | N1: Total Amount (₹) | O1: Payment Status | P1: Notes
A2: 45671 | B2: PO-2025-201 | C2: SafeGuard Equipment | D2: 29AABCG3456D4ZY | E2: INV/6110 | F2: Chemical | G2: Surface Disinfectant | H2: 80 | I2: Liters | J2: 180 | K2: =H2*J2 | L2: 0.18 | M2: =K2*L2 | N2: =K2+M2 | O2: Pending
A3: 45677 | B3: PO-2025-202 | C3: Metro Cleaning Supplies | D3: 29AABCM9012C3ZX | E3: INV/5603 | F3: Accessory | G3: Rubber Gloves | H3: 97 | I3: Pairs | J3: 45 | K3: =H3*J3 | L3: 0.18 | M3: =K3*L3 | N3: =K3+M3 | O3: Pending
A4: 45677 | B4: PO-2025-203 | C4: Metro Cleaning Supplies | D4: 29AABCM9012C3ZX | E4: INV/6152 | F4: Accessory | G4: Scrub Brush | H4: 83 | I4: Pieces | J4: 45 | K4: =H4*J4 | L4: 0.18 | M4: =K4*L4 | N4: =K4+M4 | O4: Pending
A5: 45659 | B5: PO-2025-204 | C5: Metro Cleaning Supplies | D5: 29AABCM9012C3ZX | E5: INV/3382 | F5: Chemical | G5: Floor Cleaner | H5: 33 | I5: Liters | J5: 120 | K5: =H5*J5 | L5: 0.18 | M5: =K5*L5 | N5: =K5+M5 | O5: Paid
A6: 45663 | B6: PO-2025-205 | C6: Kumar Chemicals Pvt Ltd | D6: 29AABCK1234A1ZV | E6: INV/4441 | F6: Chemical | G6: Pesticide Spray | H6: 16 | I6: Cans | J6: 350 | K6: =H6*J6 | L6: 0.18 | M6: =K6*L6 | N6: =K6+M6 | O6: Pending
A7: 45674 | B7: PO-2025-206 | C7: City Supplies | D7: 29AABCS5678B2ZW | E7: INV/2293 | F7: Chemical | G7: Surface Disinfectant | H7: 84 | I7: Liters | J7: 180 | K7: =H7*J7 | L7: 0.18 | M7: =K7*L7 | N7: =K7+M7 | O7: Pending
A8: 45683 | B8: PO-2025-207 | C8: Kumar Chemicals Pvt Ltd | D8: 29AABCK1234A1ZV | E8: INV/7554 | F8: Accessory | G8: Microfiber Cloth | H8: 69 | I8: Pieces | J8: 80 | K8: =H8*J8 | L8: 0.18 | M8: =K8*L8 | N8: =K8+M8 | O8: Pending
A9: 45670 | B9: PO-2025-208 | C9: SafeGuard Equipment | D9: 29AABCG3456D4ZY | E9: INV/9562 | F9: Accessory | G9: Rubber Gloves | H9: 70 | I9: Pairs | J9: 45 | K9: =H9*J9 | L9: 0.18 | M9: =K9*L9 | N9: =K9+M9 | O9: Paid
A10: 45662 | B10: PO-2025-209 | C10: City Supplies | D10: 29AABCS5678B2ZW | E10: INV/5918 | F10: Accessory | G10: Microfiber Cloth | H10: 86 | I10: Pieces | J10: 80 | K10: =H10*J10 | L10: 0.18 | M10: =K10*L10 | N10: =K10+M10 | O10: Paid
A11: 45668 | B11: PO-2025-210 | C11: Metro Cleaning Supplies | D11: 29AABCM9012C3ZX | E11: INV/2653 | F11: Accessory | G11: Scrub Brush | H11: 40 | I11: Pieces | J11: 45 | K11: =H11*J11 | L11: 0.18 | M11: =K11*L11 | N11: =K11+M11 | O11: Pending
A12: 45675 | B12: PO-2025-211 | C12: Kumar Chemicals Pvt Ltd | D12: 29AABCK1234A1ZV | E12: INV/1519 | F12: Chemical | G12: Glass Cleaner | H12: 47 | I12: Liters | J12: 95 | K12: =H12*J12 | L12: 0.18 | M12: =K12*L12 | N12: =K12+M12 | O12: Paid
A13: 45660 | B13: PO-2025-212 | C13: SafeGuard Equipment | D13: 29AABCG3456D4ZY | E13: INV/1526 | F13: Chemical | G13: Glass Cleaner | H13: 63 | I13: Liters | J13: 95 | K13: =H13*J13 | L13: 0.18 | M13: =K13*L13 | N13: =K13+M13 | O13: Paid
... A16: 45684 | B16: PO-2025-215 | C16: Kumar Chemicals Pvt Ltd | D16: 29AABCK1234A1ZV | E16: INV/1259 | F16: Chemical | G16: Pesticide Spray | H16: 90 | I16: Cans | J16: 350 | K16: =H16*J16 | L16: 0.18 | M16: =K16*L16 | N16: =K16+M16 | O16: Paid

Sheet Machines & Equipment
A1: Machine ID | B1: Machine Name | C1: Model | D1: Category | E1: Purchase Date | F1: Base Cost (₹) | G1: GST % | H1: GST Amount (₹) | I1: Total Cost (₹) | J1: Current Status | K1: Location/Assigned To | L1: Notes
A2: M001 | B2: Floor Scrubber | C2: Karcher BD 50/50 | D2: Cleaning Machine | E2: 45000 | F2: 72034 | G2: 0.18 | H2: =F2*G2 | I2: =F2+H2 | J2: Active | K2: Team A
A3: M002 | B3: Pressure Washer | C3: Bosch AQT 45-14X | D3: Cleaning Machine | E3: 45066 | F3: 38136 | G3: 0.18 | H3: =F3*G3 | I3: =F3+H3 | J3: Active | K3: Team B
A4: M003 | B4: Vacuum Cleaner | C4: Eureka Forbes Pro | D4: Cleaning Machine | E4: 44783 | F4: 23729 | G4: 0.18 | H4: =F4*G4 | I4: =F4+H4 | J4: Active | K4: Team A
A5: M004 | B5: Pest Control Sprayer | C5: Solo 475 | D5: Spray Equipment | E5: 44931 | F5: 12712 | G5: 0.18 | H5: =F5*G5 | I5: =F5+H5 | J5: Active | K5: Pest Team
A6: M005 | B6: Paint Sprayer | C6: Graco Magnum X5 | D6: Spray Equipment | E6: 45119 | F6: 55085 | G6: 0.18 | H6: =F6*G6 | I6: =F6+H6 | J6: Under Repair | K6: Painting Team
A7: M006 | B7: Drill Machine | C7: Bosch GSB 600 | D7: Power Tools | E7: 44669 | F7: 7203 | G7: 0.18 | H7: =F7*G7 | I7: =F7+H7 | J7: Active | K7: General
A8: M007 | B8: Angle Grinder | C8: Makita GA4030 | D8: Power Tools | E8: 44979 | F8: 5508 | G8: 0.18 | H8: =F8*G8 | I8: =F8+H8 | J8: Active | K8: General
A9: M008 | B9: Ladder (12ft) | C9: Aluminium | D9: Safety Equipment | E9: 44571 | F9: 10169 | G9: 0.18 | H9: =F9*G9 | I9: =F9+H9 | J9: Active | K9: Warehouse
A10: M009 | B10: Steam Cleaner | C10: Karcher SC3 | D10: Cleaning Machine | E10: 45299 | F10: 29661 | G10: 0.18 | H10: =F10*G10 | I10: =F10+H10 | J10: Active | K10: Team C
A11: M010 | B11: Industrial Blower | C11: Dewalt DCE100 | D11: Cleaning Machine | E11: 45235 | F11: 15254 | G11: 0.18 | H11: =F11*G11 | I11: =F11+H11 | J11: Retired | K11: Storage

Sheet Machine Maintenance
A1: Date | B1: Machine ID | C1: Machine Name | D1: Maintenance Type | E1: Description | F1: Base Cost (₹) | G1: GST % | H1: GST Amount (₹) | I1: Total Cost (₹) | J1: Done By | K1: Next Service Due | L1: Notes
A2: 45332 | B2: M001 | C2: Floor Scrubber | D2: Service | E2: Regular servicing | F2: 2119 | G2: 0.18 | H2: =F2*G2 | I2: =F2+H2 | J2: Karcher Service | K2: 45514
A3: 45366 | B3: M002 | C3: Pressure Washer | D3: Parts Replacement | E3: Nozzle replaced | F3: 1017 | G3: 0.18 | H3: =F3*G3 | I3: =F3+H3 | J3: Local Mechanic | K3: 45550
A4: 45387 | B4: M003 | C4: Vacuum Cleaner | D4: Service | E4: Filter cleaning | F4: 678 | G4: 0.18 | H4: =F4*G4 | I4: =F4+H4 | J4: In-house | K4: 45570
A5: 45432 | B5: M005 | C5: Paint Sprayer | D5: Repair | E5: Motor rewinding | F5: 7203 | G5: 0.18 | H5: =F5*G5 | I5: =F5+H5 | J5: Graco Service | K5: 45616
A6: 45451 | B6: M004 | C6: Pest Control Sprayer | D6: Service | E6: Valve check | F6: 424 | G6: 0.18 | H6: =F6*G6 | I6: =F6+H6 | J6: In-house | K6: 45634
A7: 45485 | B7: M006 | C7: Drill Machine | D7: Parts Replacement | E7: Chuck replaced | F7: 1271 | G7: 0.18 | H7: =F7*G7 | I7: =F7+H7 | J7: Bosch Service | K7: 45669
A8: 45505 | B8: M001 | C8: Floor Scrubber | D8: Service | E8: Brush replacement | F8: 3814 | G8: 0.18 | H8: =F8*G8 | I8: =F8+H8 | J8: Karcher Service | K8: 45689
A9: 45522 | B9: M007 | C9: Angle Grinder | D9: Repair | E9: Switch repair | F9: 508 | G9: 0.18 | H9: =F9*G9 | I9: =F9+H9 | J9: Local Mechanic | K9: 45706
A10: 45540 | B10: M009 | C10: Steam Cleaner | D10: Service | E10: Descaling | F10: 1017 | G10: 0.18 | H10: =F10*G10 | I10: =F10+H10 | J10: Karcher Service | K10: 45721
A11: 45575 | B11: M002 | C11: Pressure Washer | D11: Service | E11: Regular maintenance | F11: 1525 | G11: 0.18 | H11: =F11*G11 | I11: =F11+H11 | J11: Bosch Service | K11: 45757

Sheet Chemicals Stock
A1: Item ID | B1: Chemical Name | C1: Brand | D1: Category | E1: Unit | F1: Opening Stock | G1: Stock Added | H1: Stock Used | I1: Closing Stock | J1: Min Level | K1: Status | L1: Last Updated
A2: CH001 | B2: Floor Cleaner | C2: Lizol | D2: Cleaning Agents | E2: Liters | F2: 50 | G2: 100 | H2: 80 | I2: =F2+G2-H2 | J2: 20 | K2: =IF(I2<J2,"Low Stock","OK") | L2: 45682
A3: CH002 | B3: Glass Cleaner | C3: Colin | D3: Cleaning Agents | E3: Liters | F3: 30 | G3: 50 | H3: 45 | I3: =F3+G3-H3 | J3: 15 | K3: =IF(I3<J3,"Low Stock","OK") | L3: 45682
A4: CH003 | B4: Toilet Cleaner | C4: Harpic | D4: Cleaning Agents | E4: Liters | F4: 40 | G4: 80 | H4: 70 | I4: =F4+G4-H4 | J4: 20 | K4: =IF(I4<J4,"Low Stock","OK") | L4: 45682
A5: CH004 | B5: Pesticide Spray | C5: Baygon Pro | D5: Pest Control | E5: Cans | F5: 25 | G5: 50 | H5: 55 | I5: =F5+G5-H5 | J5: 10 | K5: =IF(I5<J5,"Low Stock","OK") | L5: 45682
A6: CH005 | B6: Termite Solution | C6: Premise | D6: Pest Control | E6: Liters | F6: 20 | G6: 40 | H6: 35 | I6: =F6+G6-H6 | J6: 10 | K6: =IF(I6<J6,"Low Stock","OK") | L6: 45682
A7: CH006 | B7: Hand Sanitizer | C7: Dettol | D7: Sanitizers | E7: Liters | F7: 15 | G7: 30 | H7: 28 | I7: =F7+G7-H7 | J7: 10 | K7: =IF(I7<J7,"Low Stock","OK") | L7: 45682
A8: CH007 | B8: Surface Disinfectant | C8: Lysol | D8: Sanitizers | E8: Liters | F8: 25 | G8: 50 | H8: 40 | I8: =F8+G8-H8 | J8: 15 | K8: =IF(I8<J8,"Low Stock","OK") | L8: 45682
A9: CH008 | B9: Degreaser | C9: WD-40 | D9: Specialty | E9: Cans | F9: 10 | G9: 20 | H9: 18 | I9: =F9+G9-H9 | J9: 5 | K9: =IF(I9<J9,"Low Stock","OK") | L9: 45682
A10: CH009 | B10: Stain Remover | C10: Vanish | D10: Specialty | E10: KG | F10: 8 | G10: 15 | H10: 12 | I10: =F10+G10-H10 | J10: 5 | K10: =IF(I10<J10,"Low Stock","OK") | L10: 45682
A11: CH010 | B11: Air Freshener | C11: Odonil | D11: Specialty | E11: Cans | F11: 30 | G11: 60 | H11: 65 | I11: =F11+G11-H11 | J11: 15 | K11: =IF(I11<J11,"Low Stock","OK") | L11: 45682
A12: CH011 | B12: Cockroach Gel | C12: Advion | D12: Pest Control | E12: Bottles | F12: 20 | G12: 30 | H12: 25 | I12: =F12+G12-H12 | J12: 10 | K12: =IF(I12<J12,"Low Stock","OK") | L12: 45682
A13: CH012 | B13: Fabric Softener | C13: Comfort | D13: Cleaning Agents | E13: Liters | F13: 15 | G13: 25 | H13: 22 | I13: =F13+G13-H13 | J13: 10 | K13: =IF(I13<J13,"Low Stock","OK") | L13: 45682

Sheet Accessories Stock
A1: Item ID | B1: Item Name | C1: Category | D1: Unit | E1: Opening Stock | F1: Stock Added | G1: Stock Used | H1: Closing Stock | I1: Min Level | J1: Status | K1: Last Updated
A2: AC001 | B2: Rubber Hose (10m) | C2: Pipes & Hoses | D2: Pieces | E2: 10 | F2: 15 | G2: 12 | H2: =E2+F2-G2 | I2: 5 | J2: =IF(H2<I2,"Low Stock","OK") | K2: 45682
A3: AC002 | B3: Floor Mop | C3: Brushes & Mops | D3: Pieces | E3: 20 | F3: 30 | G3: 28 | H3: =E3+F3-G3 | I3: 10 | J3: =IF(H3<I3,"Low Stock","OK") | K3: 45682
A4: AC003 | B4: Scrub Brush | C4: Brushes & Mops | D4: Pieces | E4: 25 | F4: 40 | G4: 35 | H4: =E4+F4-G4 | I4: 10 | J4: =IF(H4<I4,"Low Stock","OK") | K4: 45682
A5: AC004 | B5: Microfiber Cloth | C5: Cloths & Wipes | D5: Pieces | E5: 50 | F5: 100 | G5: 90 | H5: =E5+F5-G5 | I5: 25 | J5: =IF(H5<I5,"Low Stock","OK") | K5: 45682
A6: AC005 | B6: Rubber Gloves | C6: Gloves & Safety | D6: Pairs | E6: 30 | F6: 50 | G6: 48 | H6: =E6+F6-G6 | I6: 15 | J6: =IF(H6<I6,"Low Stock","OK") | K6: 45682
A7: AC006 | B7: Safety Goggles | C7: Gloves & Safety | D7: Pieces | E7: 10 | F7: 15 | G7: 8 | H7: =E7+F7-G7 | I7: 5 | J7: =IF(H7<I7,"Low Stock","OK") | K7: 45682
A8: AC007 | B8: Spray Bottles | C8: Other | D8: Pieces | E8: 20 | F8: 30 | G8: 22 | H8: =E8+F8-G8 | I8: 10 | J8: =IF(H8<I8,"Low Stock","OK") | K8: 45682
A9: AC008 | B9: Dust Pan Set | C9: Brushes & Mops | D9: Sets | E9: 15 | F9: 20 | G9: 18 | H9: =E9+F9-G9 | I9: 8 | J9: =IF(H9<I9,"Low Stock","OK") | K9: 45682
A10: AC009 | B10: Extension Cord | C10: Tools | D10: Pieces | E10: 8 | F10: 10 | G10: 7 | H10: =E10+F10-G10 | I10: 4 | J10: =IF(H10<I10,"Low Stock","OK") | K10: 45682
A11: AC010 | B11: Bucket (20L) | C11: Other | D11: Pieces | E11: 25 | F11: 30 | G11: 28 | H11: =E11+F11-G11 | I11: 10 | J11: =IF(H11<I11,"Low Stock","OK") | K11: 45682
A12: AC011 | B12: Face Masks | C12: Gloves & Safety | D12: Boxes | E12: 10 | F12: 20 | G12: 18 | H12: =E12+F12-G12 | I12: 5 | J12: =IF(H12<I12,"Low Stock","OK") | K12: 45682
A13: AC012 | B13: Sponge Pack | C13: Cloths & Wipes | D13: Packs | E13: 20 | F13: 35 | G13: 30 | H13: =E13+F13-G13 | I13: 10 | J13: =IF(H13<I13,"Low Stock","OK") | K13: 45682

Sheet Stock Transactions
A1: Date | B1: Transaction ID | C1: Item Type | D1: Item ID | E1: Item Name | F1: Transaction Type | G1: Quantity | H1: Unit Rate (₹) | I1: GST % | J1: GST Amount (₹) | K1: Total Cost (₹) | L1: Project/Team | M1: Notes
A2: 45659 | B2: TXN001 | C2: Chemical | D2: CH001 | E2: Floor Cleaner | F2: Purchase | G2: 50 | H2: 120 | I2: 0.18 | J2: =G2*H2*I2 | K2: =G2*H2+J2 | L2: Warehouse | M2: Monthly stock
A3: 45660 | B3: TXN002 | C3: Chemical | D3: CH004 | E3: Pesticide Spray | F3: Purchase | G3: 25 | H3: 350 | I3: 0.18 | J3: =G3*H3*I3 | K3: =G3*H3+J3 | L3: Warehouse
A4: 45662 | B4: TXN003 | C4: Accessory | D4: AC004 | E4: Microfiber Cloth | F4: Purchase | G4: 50 | H4: 80 | I4: 0.18 | J4: =G4*H4*I4 | K4: =G4*H4+J4 | L4: Warehouse | M4: Bulk order
A5: 45663 | B5: TXN004 | C5: Chemical | D5: CH001 | E5: Floor Cleaner | F5: Used | G5: 20 | H5: 0 | I5: 0 | J5: =G5*H5*I5 | K5: =G5*H5+J5 | L5: Team A | M5: Green Valley project
A6: 45664 | B6: TXN005 | C6: Accessory | D6: AC005 | E6: Rubber Gloves | F6: Used | G6: 10 | H6: 0 | I6: 0 | J6: =G6*H6*I6 | K6: =G6*H6+J6 | L6: Team B
A7: 45665 | B7: TXN006 | C7: Chemical | D7: CH002 | E7: Glass Cleaner | F7: Purchase | G7: 25 | H7: 95 | I7: 0.18 | J7: =G7*H7*I7 | K7: =G7*H7+J7 | L7: Warehouse
A8: 45667 | B8: TXN007 | C8: Accessory | D8: AC002 | E8: Floor Mop | F8: Damaged | G8: 2 | H8: 0 | I8: 0 | J8: =G8*H8*I8 | K8: =G8*H8+J8 | L8: Team A | M8: Worn out
A9: 45668 | B9: TXN008 | C9: Chemical | D9: CH007 | E9: Surface Disinfectant | F9: Used | G9: 15 | H9: 0 | I9: 0 | J9: =G9*H9*I9 | K9: =G9*H9+J9 | L9: Team C | M9: Hospital contract
A10: 45669 | B10: TXN009 | C10: Accessory | D10: AC003 | E10: Scrub Brush | F10: Purchase | G10: 20 | H10: 45 | I10: 0.18 | J10: =G10*H10*I10 | K10: =G10*H10+J10 | L10: Warehouse
A11: 45671 | B11: TXN010 | C11: Chemical | D11: CH005 | E11: Termite Solution | F11: Purchase | G11: 20 | H11: 850 | I11: 0.18 | J11: =G11*H11*I11 | K11: =G11*H11+J11 | L11: Warehouse

Sheet Income Summary
A1: INCOME SUMMARY REPORT
A3: SERVICE-WISE REVENUE
A4: Service Type | B4: Base Revenue (₹) | C4: GST Collected (₹) | D4: Total Revenue (₹) | E4: Order Count
A5: Deep Cleaning | B5: =SUMIF('Income Tracker'!D:D,A5,'Income Tracker'!G:G) | C5: =SUMIF('Income Tracker'!D:D,A5,'Income Tracker'!I:I) | D5: =SUMIF('Income Tracker'!D:D,A5,'Income Tracker'!J:J) | E5: =COUNTIF('Income Tracker'!D:D,A5)
A6: Regular Cleaning | B6: =SUMIF('Income Tracker'!D:D,A6,'Income Tracker'!G:G) | C6: =SUMIF('Income Tracker'!D:D,A6,'Income Tracker'!I:I) | D6: =SUMIF('Income Tracker'!D:D,A6,'Income Tracker'!J:J) | E6: =COUNTIF('Income Tracker'!D:D,A6)
A7: Pest Control | B7: =SUMIF('Income Tracker'!D:D,A7,'Income Tracker'!G:G) | C7: =SUMIF('Income Tracker'!D:D,A7,'Income Tracker'!I:I) | D7: =SUMIF('Income Tracker'!D:D,A7,'Income Tracker'!J:J) | E7: =COUNTIF('Income Tracker'!D:D,A7)
A8: Painting | B8: =SUMIF('Income Tracker'!D:D,A8,'Income Tracker'!G:G) | C8: =SUMIF('Income Tracker'!D:D,A8,'Income Tracker'!I:I) | D8: =SUMIF('Income Tracker'!D:D,A8,'Income Tracker'!J:J) | E8: =COUNTIF('Income Tracker'!D:D,A8)
A9: Plumbing | B9: =SUMIF('Income Tracker'!D:D,A9,'Income Tracker'!G:G) | C9: =SUMIF('Income Tracker'!D:D,A9,'Income Tracker'!I:I) | D9: =SUMIF('Income Tracker'!D:D,A9,'Income Tracker'!J:J) | E9: =COUNTIF('Income Tracker'!D:D,A9)
A10: Electrical | B10: =SUMIF('Income Tracker'!D:D,A10,'Income Tracker'!G:G) | C10: =SUMIF('Income Tracker'!D:D,A10,'Income Tracker'!I:I) | D10: =SUMIF('Income Tracker'!D:D,A10,'Income Tracker'!J:J) | E10: =COUNTIF('Income Tracker'!D:D,A10)
A11: Carpentry | B11: =SUMIF('Income Tracker'!D:D,A11,'Income Tracker'!G:G) | C11: =SUMIF('Income Tracker'!D:D,A11,'Income Tracker'!I:I) | D11: =SUMIF('Income Tracker'!D:D,A11,'Income Tracker'!J:J) | E11: =COUNTIF('Income Tracker'!D:D,A11)
A12: AC Service | B12: =SUMIF('Income Tracker'!D:D,A12,'Income Tracker'!G:G) | C12: =SUMIF('Income Tracker'!D:D,A12,'Income Tracker'!I:I) | D12: =SUMIF('Income Tracker'!D:D,A12,'Income Tracker'!J:J) | E12: =COUNTIF('Income Tracker'!D:D,A12)
A13: TOTAL | B13: =SUM(B5:B12) | C13: =SUM(C5:C12) | D13: =SUM(D5:D12) | E13: =SUM(E5:E12)

Sheet Expense Summary
A1: EXPENSE SUMMARY REPORT
A3: CATEGORY-WISE EXPENSES
A4: Category | B4: Base Amount (₹) | C4: GST Paid (₹) | D4: Total Amount (₹) | E4: Transaction Count
A5: Staff Salary | B5: =SUMIF('Expense Tracker'!C:C,A5,'Expense Tracker'!F:F) | C5: =SUMIF('Expense Tracker'!C:C,A5,'Expense Tracker'!H:H) | D5: =SUMIF('Expense Tracker'!C:C,A5,'Expense Tracker'!I:I) | E5: =COUNTIF('Expense Tracker'!C:C,A5)
A6: Vendor Payment | B6: =SUMIF('Expense Tracker'!C:C,A6,'Expense Tracker'!F:F) | C6: =SUMIF('Expense Tracker'!C:C,A6,'Expense Tracker'!H:H) | D6: =SUMIF('Expense Tracker'!C:C,A6,'Expense Tracker'!I:I) | E6: =COUNTIF('Expense Tracker'!C:C,A6)
A7: Travel & Fuel | B7: =SUMIF('Expense Tracker'!C:C,A7,'Expense Tracker'!F:F) | C7: =SUMIF('Expense Tracker'!C:C,A7,'Expense Tracker'!H:H) | D7: =SUMIF('Expense Tracker'!C:C,A7,'Expense Tracker'!I:I) | E7: =COUNTIF('Expense Tracker'!C:C,A7)
A8: Marketing | B8: =SUMIF('Expense Tracker'!C:C,A8,'Expense Tracker'!F:F) | C8: =SUMIF('Expense Tracker'!C:C,A8,'Expense Tracker'!H:H) | D8: =SUMIF('Expense Tracker'!C:C,A8,'Expense Tracker'!I:I) | E8: =COUNTIF('Expense Tracker'!C:C,A8)
A9: Office Expenses | B9: =SUMIF('Expense Tracker'!C:C,A9,'Expense Tracker'!F:F) | C9: =SUMIF('Expense Tracker'!C:C,A9,'Expense Tracker'!H:H) | D9: =SUMIF('Expense Tracker'!C:C,A9,'Expense Tracker'!I:I) | E9: =COUNTIF('Expense Tracker'!C:C,A9)
A10: Miscellaneous | B10: =SUMIF('Expense Tracker'!C:C,A10,'Expense Tracker'!F:F) | C10: =SUMIF('Expense Tracker'!C:C,A10,'Expense Tracker'!H:H) | D10: =SUMIF('Expense Tracker'!C:C,A10,'Expense Tracker'!I:I) | E10: =COUNTIF('Expense Tracker'!C:C,A10)
A11: TOTAL | B11: =SUM(B5:B10) | C11: =SUM(C5:C10) | D11: =SUM(D5:D10) | E11: =SUM(E5:E10)

Sheet GST Summary
A1: GST SUMMARY REPORT
A2: (For GST Filing Reference)
A4: GST COLLECTED (OUTPUT TAX)
A5: Source | B5: Base Amount (₹) | C5: GST Amount (₹)
A6: Income from Services | B6: =SUM('Income Tracker'!G:G) | C6: =SUM('Income Tracker'!I:I)
A7: TOTAL GST COLLECTED | B7: =B6 | C7: =C6
A10: GST PAID (INPUT TAX)
A11: Source | B11: Base Amount (₹) | C11: GST Amount (₹)
A12: Expenses | B12: =SUM('Expense Tracker'!F:F) | C12: =SUM('Expense Tracker'!H:H)
A13: Stock Purchases | B13: =SUM('Stock Purchases'!K:K) | C13: =SUM('Stock Purchases'!M:M)
A14: Machine Purchases | B14: =SUM('Machines & Equipment'!F:F) | C14: =SUM('Machines & Equipment'!H:H)
A15: Machine Maintenance | B15: =SUM('Machine Maintenance'!F:F) | C15: =SUM('Machine Maintenance'!H:H)
A16: TOTAL GST PAID | B16: =SUM(B12:B15) | C16: =SUM(C12:C15)
A19: NET GST PAYABLE | C19: =C7-C16
A21: Note: Positive value = GST to pay to government
A22: Negative value = GST credit (Input Tax Credit)

Sheet Profitability Report
A1: PROFITABILITY ANALYSIS
A3: OVERALL PROFITABILITY
A4: Metric | B4: Amount (₹)
A5: Total Revenue (excl. GST) | B5: =SUM('Income Tracker'!G:G)
A6: Total Expenses (excl. GST) | B6: =SUM('Expense Tracker'!F:F)
A7: Gross Profit | B7: =B5-B6
A8: Profit Margin % | B8: =IF(B5>0,B7/B5,0)

Sheet Stock Reports
A1: STOCK & INVENTORY REPORTS
A3: TOTAL ASSET VALUE
A4: Category | B4: Base Value (₹) | C4: GST Paid (₹) | D4: Total Value (₹) | E4: Count
A5: Cleaning Machine | B5: =SUMIF('Machines & Equipment'!D:D,A5,'Machines & Equipment'!F:F) | C5: =SUMIF('Machines & Equipment'!D:D,A5,'Machines & Equipment'!H:H) | D5: =SUMIF('Machines & Equipment'!D:D,A5,'Machines & Equipment'!I:I) | E5: =COUNTIF('Machines & Equipment'!D:D,A5)
A6: Spray Equipment | B6: =SUMIF('Machines & Equipment'!D:D,A6,'Machines & Equipment'!F:F) | C6: =SUMIF('Machines & Equipment'!D:D,A6,'Machines & Equipment'!H:H) | D6: =SUMIF('Machines & Equipment'!D:D,A6,'Machines & Equipment'!I:I) | E6: =COUNTIF('Machines & Equipment'!D:D,A6)
A7: Power Tools | B7: =SUMIF('Machines & Equipment'!D:D,A7,'Machines & Equipment'!F:F) | C7: =SUMIF('Machines & Equipment'!D:D,A7,'Machines & Equipment'!H:H) | D7: =SUMIF('Machines & Equipment'!D:D,A7,'Machines & Equipment'!I:I) | E7: =COUNTIF('Machines & Equipment'!D:D,A7)
A8: Safety Equipment | B8: =SUMIF('Machines & Equipment'!D:D,A8,'Machines & Equipment'!F:F) | C8: =SUMIF('Machines & Equipment'!D:D,A8,'Machines & Equipment'!H:H) | D8: =SUMIF('Machines & Equipment'!D:D,A8,'Machines & Equipment'!I:I) | E8: =COUNTIF('Machines & Equipment'!D:D,A8)
A9: TOTAL | B9: =SUM(B5:B8) | C9: =SUM(C5:C8) | D9: =SUM(D5:D8) | E9: =SUM(E5:E8)
A12: STOCK PURCHASE SUMMARY
A13: Total Stock Purchases (Base) | B13: =SUM('Stock Purchases'!K:K)
A14: Total GST on Purchases | B14: =SUM('Stock Purchases'!M:M)
A15: Total with GST | B15: =SUM('Stock Purchases'!N:N)

Sheet Dashboard
A1: MIS DASHBOARD
A3: KEY PERFORMANCE INDICATORS
A5: Total Revenue | B5: =SUM('Income Tracker'!J:J) | C5: Total Expenses | D5: =SUM('Expense Tracker'!I:I) | E5: Net Profit | F5: =B5-D5 | G5: Profit Margin | H5: =IF(B5>0,F5/B5,0)
A7: GST Collected | B7: =SUM('Income Tracker'!I:I) | C7: GST Paid | D7: =SUM('Expense Tracker'!H:H)+SUM('Stock Purchases'!M:M) | E7: Net GST Payable | F7: =B7-D7 | G7: Total Assets | H7: =SUM('Machines & Equipment'!I:I)
A10: CHARTS DATA
A11: Category | B11: Amount | D11: Service | E11: Revenue | G11: Expense Category | H11: Amount
A12: Revenue | B12: =SUM('Income Tracker'!J:J) | D12: Deep Cleaning | E12: =SUMIF('Income Tracker'!D:D,D12,'Income Tracker'!J:J) | G12: Staff Salary | H12: =SUMIF('Expense Tracker'!C:C,G12,'Expense Tracker'!I:I)
A13: Expenses | B13: =SUM('Expense Tracker'!I:I) | D13: Regular Cleaning | E13: =SUMIF('Income Tracker'!D:D,D13,'Income Tracker'!J:J) | G13: Vendor Payment | H13: =SUMIF('Expense Tracker'!C:C,G13,'Expense Tracker'!I:I)
D14: Pest Control | E14: =SUMIF('Income Tracker'!D:D,D14,'Income Tracker'!J:J) | G14: Travel & Fuel | H14: =SUMIF('Expense Tracker'!C:C,G14,'Expense Tracker'!I:I)
D15: Painting | E15: =SUMIF('Income Tracker'!D:D,D15,'Income Tracker'!J:J) | G15: Marketing | H15: =SUMIF('Expense Tracker'!C:C,G15,'Expense Tracker'!I:I)
D16: Plumbing | E16: =SUMIF('Income Tracker'!D:D,D16,'Income Tracker'!J:J) | G16: Office Expenses | H16: =SUMIF('Expense Tracker'!C:C,G16,'Expense Tracker'!I:I)
D17: Electrical | E17: =SUMIF('Income Tracker'!D:D,D17,'Income Tracker'!J:J) | G17: Miscellaneous | H17: =SUMIF('Expense Tracker'!C:C,G17,'Expense Tracker'!I:I)
D18: Carpentry | E18: =SUMIF('Income Tracker'!D:D,D18,'Income Tracker'!J:J)
D19: AC Service | E19: =SUMIF('Income Tracker'!D:D,D19,'Income Tracker'!J:J)
